{"v":"4.9.0","fr":24,"ip":0,"op":45,"w":380,"h":650,"nm":"strikeIdle","ddd":0,"assets":[{"id":"comp_0","layers":[{"ddd":0,"ind":1,"ty":4,"nm":"X_light","sr":1,"ks":{"o":{"a":0,"k":100},"r":{"a":0,"k":0},"p":{"a":0,"k":[327.431,550.279,0]},"a":{"a":0,"k":[144.664,178.52,0]},"s":{"a":0,"k":[100,100,100]}},"ao":0,"shapes":[{"ty":"gr","it":[{"ind":0,"ty":"sh","ix":1,"ks":{"a":0,"k":{"i":[[0,-1.621],[1.621,0],[0,1.621],[-1.62,0]],"o":[[0,1.621],[-1.62,0],[0,-1.621],[1.621,0]],"v":[[2.935,0],[-0.001,2.935],[-2.935,0],[-0.001,-2.935]],"c":true}},"nm":"Path 1","mn":"ADBE Vector Shape - Group"},{"ty":"fl","c":{"a":0,"k":[1,1,1,1]},"o":{"a":0,"k":100},"r":1,"nm":"Fill 1","mn":"ADBE Vector Graphic - Fill"},{"ty":"tr","p":{"a":0,"k":[235.792,62.291],"ix":2},"a":{"a":0,"k":[0,0],"ix":1},"s":{"a":0,"k":[207,207],"ix":3},"r":{"a":0,"k":0,"ix":6},"o":{"a":0,"k":100,"ix":7},"sk":{"a":0,"k":0,"ix":4},"sa":{"a":0,"k":0,"ix":5},"nm":"Transform"}],"nm":"Group 7","np":2,"cix":2,"ix":1,"mn":"ADBE Vector Group"},{"ty":"gr","it":[{"ind":0,"ty":"sh","ix":1,"ks":{"a":0,"k":{"i":[[0,-4.143],[4.128,0],[0,4.142],[-4.128,0]],"o":[[0,4.142],[-4.128,0],[0,-4.143],[4.128,0]],"v":[[7.474,0],[0,7.5],[-7.474,0],[0,-7.5]],"c":true}},"nm":"Path 1","mn":"ADBE Vector Shape - Group"},{"ty":"fl","c":{"a":0,"k":[1,0.267,0.357,1]},"o":{"a":0,"k":100},"r":1,"nm":"Fill 1","mn":"ADBE Vector Graphic - Fill"},{"ty":"tr","p":{"a":0,"k":[235.792,62.292],"ix":2},"a":{"a":0,"k":[0,0],"ix":1},"s":{"a":0,"k":[159,159],"ix":3},"r":{"a":0,"k":0,"ix":6},"o":{"a":0,"k":100,"ix":7},"sk":{"a":0,"k":0,"ix":4},"sa":{"a":0,"k":0,"ix":5},"nm":"Transform"}],"nm":"Group 8","np":2,"cix":2,"ix":2,"mn":"ADBE Vector Group"},{"ty":"gr","it":[{"ind":0,"ty":"sh","ix":1,"ks":{"a":0,"k":{"i":[[0,-1.621],[1.621,0],[0,1.621],[-1.62,0]],"o":[[0,1.621],[-1.62,0],[0,-1.621],[1.621,0]],"v":[[2.935,0],[-0.001,2.935],[-2.935,0],[-0.001,-2.935]],"c":true}},"nm":"Path 1","mn":"ADBE Vector Shape - Group"},{"ty":"fl","c":{"a":0,"k":[1,1,1,1]},"o":{"a":0,"k":100},"r":1,"nm":"Fill 1","mn":"ADBE Vector Graphic - Fill"},{"ty":"tr","p":{"a":0,"k":[199.792,62.291],"ix":2},"a":{"a":0,"k":[0,0],"ix":1},"s":{"a":0,"k":[207,207],"ix":3},"r":{"a":0,"k":0,"ix":6},"o":{"a":0,"k":100,"ix":7},"sk":{"a":0,"k":0,"ix":4},"sa":{"a":0,"k":0,"ix":5},"nm":"Transform"}],"nm":"Group 11","np":2,"cix":2,"ix":3,"mn":"ADBE Vector Group"},{"ty":"gr","it":[{"ind":0,"ty":"sh","ix":1,"ks":{"a":0,"k":{"i":[[0,-4.143],[4.128,0],[0,4.142],[-4.128,0]],"o":[[0,4.142],[-4.128,0],[0,-4.143],[4.128,0]],"v":[[7.474,0],[0,7.5],[-7.474,0],[0,-7.5]],"c":true}},"nm":"Path 1","mn":"ADBE Vector Shape - Group"},{"ty":"fl","c":{"a":0,"k":[1,0.267,0.357,1]},"o":{"a":0,"k":100},"r":1,"nm":"Fill 1","mn":"ADBE Vector Graphic - Fill"},{"ty":"tr","p":{"a":0,"k":[199.792,62.292],"ix":2},"a":{"a":0,"k":[0,0],"ix":1},"s":{"a":0,"k":[159,159],"ix":3},"r":{"a":0,"k":0,"ix":6},"o":{"a":0,"k":100,"ix":7},"sk":{"a":0,"k":0,"ix":4},"sa":{"a":0,"k":0,"ix":5},"nm":"Transform"}],"nm":"Group 12","np":2,"cix":2,"ix":4,"mn":"ADBE Vector Group"},{"ty":"gr","it":[{"ind":0,"ty":"sh","ix":1,"ks":{"a":0,"k":{"i":[[0,-1.621],[1.621,0],[0,1.621],[-1.62,0]],"o":[[0,1.621],[-1.62,0],[0,-1.621],[1.621,0]],"v":[[2.935,-0.001],[-0.001,2.935],[-2.935,-0.001],[-0.001,-2.935]],"c":true}},"nm":"Path 1","mn":"ADBE Vector Shape - Group"},{"ty":"fl","c":{"a":0,"k":[1,1,1,1]},"o":{"a":0,"k":100},"r":1,"nm":"Fill 1","mn":"ADBE Vector Graphic - Fill"},{"ty":"tr","p":{"a":0,"k":[255.017,35.363],"ix":2},"a":{"a":0,"k":[0,0],"ix":1},"s":{"a":0,"k":[207,207],"ix":3},"r":{"a":0,"k":0,"ix":6},"o":{"a":0,"k":100,"ix":7},"sk":{"a":0,"k":0,"ix":4},"sa":{"a":0,"k":0,"ix":5},"nm":"Transform"}],"nm":"Group 19","np":2,"cix":2,"ix":5,"mn":"ADBE Vector Group"},{"ty":"gr","it":[{"ind":0,"ty":"sh","ix":1,"ks":{"a":0,"k":{"i":[[0,-4.142],[4.128,0],[0,4.142],[-4.128,0]],"o":[[0,4.142],[-4.128,0],[0,-4.142],[4.128,0]],"v":[[7.475,0],[-0.001,7.5],[-7.475,0],[-0.001,-7.5]],"c":true}},"nm":"Path 1","mn":"ADBE Vector Shape - Group"},{"ty":"fl","c":{"a":0,"k":[1,0.267,0.357,1]},"o":{"a":0,"k":100},"r":1,"nm":"Fill 1","mn":"ADBE Vector Graphic - Fill"},{"ty":"tr","p":{"a":0,"k":[255.017,35.362],"ix":2},"a":{"a":0,"k":[0,0],"ix":1},"s":{"a":0,"k":[159,159],"ix":3},"r":{"a":0,"k":0,"ix":6},"o":{"a":0,"k":100,"ix":7},"sk":{"a":0,"k":0,"ix":4},"sa":{"a":0,"k":0,"ix":5},"nm":"Transform"}],"nm":"Group 20","np":2,"cix":2,"ix":6,"mn":"ADBE Vector Group"},{"ty":"gr","it":[{"ind":0,"ty":"sh","ix":1,"ks":{"a":0,"k":{"i":[[0,-1.621],[1.621,0],[0,1.621],[-1.62,0]],"o":[[0,1.621],[-1.62,0],[0,-1.621],[1.621,0]],"v":[[2.935,-0.001],[-0.001,2.935],[-2.935,-0.001],[-0.001,-2.935]],"c":true}},"nm":"Path 1","mn":"ADBE Vector Shape - Group"},{"ty":"fl","c":{"a":0,"k":[1,1,1,1]},"o":{"a":0,"k":100},"r":1,"nm":"Fill 1","mn":"ADBE Vector Graphic - Fill"},{"ty":"tr","p":{"a":0,"k":[219.017,35.363],"ix":2},"a":{"a":0,"k":[0,0],"ix":1},"s":{"a":0,"k":[207,207],"ix":3},"r":{"a":0,"k":0,"ix":6},"o":{"a":0,"k":100,"ix":7},"sk":{"a":0,"k":0,"ix":4},"sa":{"a":0,"k":0,"ix":5},"nm":"Transform"}],"nm":"Group 23","np":2,"cix":2,"ix":7,"mn":"ADBE Vector Group"},{"ty":"gr","it":[{"ind":0,"ty":"sh","ix":1,"ks":{"a":0,"k":{"i":[[0,-4.142],[4.128,0],[0,4.142],[-4.128,0]],"o":[[0,4.142],[-4.128,0],[0,-4.142],[4.128,0]],"v":[[7.475,0],[-0.001,7.5],[-7.475,0],[-0.001,-7.5]],"c":true}},"nm":"Path 1","mn":"ADBE Vector Shape - Group"},{"ty":"fl","c":{"a":0,"k":[1,0.267,0.357,1]},"o":{"a":0,"k":100},"r":1,"nm":"Fill 1","mn":"ADBE Vector Graphic - Fill"},{"ty":"tr","p":{"a":0,"k":[219.017,35.362],"ix":2},"a":{"a":0,"k":[0,0],"ix":1},"s":{"a":0,"k":[159,159],"ix":3},"r":{"a":0,"k":0,"ix":6},"o":{"a":0,"k":100,"ix":7},"sk":{"a":0,"k":0,"ix":4},"sa":{"a":0,"k":0,"ix":5},"nm":"Transform"}],"nm":"Group 24","np":2,"cix":2,"ix":8,"mn":"ADBE Vector Group"},{"ty":"gr","it":[{"ind":0,"ty":"sh","ix":1,"ks":{"a":0,"k":{"i":[[0,-1.621],[1.621,0],[0,1.621],[-1.62,0]],"o":[[0,1.621],[-1.62,0],[0,-1.621],[1.621,0]],"v":[[2.935,0],[-0.001,2.935],[-2.935,0],[-0.001,-2.935]],"c":true}},"nm":"Path 1","mn":"ADBE Vector Shape - Group"},{"ty":"fl","c":{"a":0,"k":[1,1,1,1]},"o":{"a":0,"k":100},"r":1,"nm":"Fill 1","mn":"ADBE Vector Graphic - Fill"},{"ty":"tr","p":{"a":0,"k":[217.003,89.22],"ix":2},"a":{"a":0,"k":[0,0],"ix":1},"s":{"a":0,"k":[207,207],"ix":3},"r":{"a":0,"k":0,"ix":6},"o":{"a":0,"k":100,"ix":7},"sk":{"a":0,"k":0,"ix":4},"sa":{"a":0,"k":0,"ix":5},"nm":"Transform"}],"nm":"Group 37","np":2,"cix":2,"ix":9,"mn":"ADBE Vector Group"},{"ty":"gr","it":[{"ind":0,"ty":"sh","ix":1,"ks":{"a":0,"k":{"i":[[0,-4.142],[4.128,0],[0,4.142],[-4.128,0]],"o":[[0,4.142],[-4.128,0],[0,-4.142],[4.128,0]],"v":[[7.475,0],[0,7.5],[-7.475,0],[0,-7.5]],"c":true}},"nm":"Path 1","mn":"ADBE Vector Shape - Group"},{"ty":"fl","c":{"a":0,"k":[1,0.267,0.357,1]},"o":{"a":0,"k":100},"r":1,"nm":"Fill 1","mn":"ADBE Vector Graphic - Fill"},{"ty":"tr","p":{"a":0,"k":[217.002,89.22],"ix":2},"a":{"a":0,"k":[0,0],"ix":1},"s":{"a":0,"k":[159,159],"ix":3},"r":{"a":0,"k":0,"ix":6},"o":{"a":0,"k":100,"ix":7},"sk":{"a":0,"k":0,"ix":4},"sa":{"a":0,"k":0,"ix":5},"nm":"Transform"}],"nm":"Group 38","np":2,"cix":2,"ix":10,"mn":"ADBE Vector Group"},{"ty":"gr","it":[{"ind":0,"ty":"sh","ix":1,"ks":{"a":0,"k":{"i":[[0,-1.621],[1.621,0],[0,1.621],[-1.62,0]],"o":[[0,1.621],[-1.62,0],[0,-1.621],[1.621,0]],"v":[[2.935,0],[-0.001,2.935],[-2.935,0],[-0.001,-2.935]],"c":true}},"nm":"Path 1","mn":"ADBE Vector Shape - Group"},{"ty":"fl","c":{"a":0,"k":[1,1,1,1]},"o":{"a":0,"k":100},"r":1,"nm":"Fill 1","mn":"ADBE Vector Graphic - Fill"},{"ty":"tr","p":{"a":0,"k":[181.003,89.22],"ix":2},"a":{"a":0,"k":[0,0],"ix":1},"s":{"a":0,"k":[207,207],"ix":3},"r":{"a":0,"k":0,"ix":6},"o":{"a":0,"k":100,"ix":7},"sk":{"a":0,"k":0,"ix":4},"sa":{"a":0,"k":0,"ix":5},"nm":"Transform"}],"nm":"Group 41","np":2,"cix":2,"ix":11,"mn":"ADBE Vector Group"},{"ty":"gr","it":[{"ind":0,"ty":"sh","ix":1,"ks":{"a":0,"k":{"i":[[0,-4.142],[4.128,0],[0,4.142],[-4.128,0]],"o":[[0,4.142],[-4.128,0],[0,-4.142],[4.128,0]],"v":[[7.475,0],[0,7.5],[-7.475,0],[0,-7.5]],"c":true}},"nm":"Path 1","mn":"ADBE Vector Shape - Group"},{"ty":"fl","c":{"a":0,"k":[1,0.267,0.357,1]},"o":{"a":0,"k":100},"r":1,"nm":"Fill 1","mn":"ADBE Vector Graphic - Fill"},{"ty":"tr","p":{"a":0,"k":[181.002,89.22],"ix":2},"a":{"a":0,"k":[0,0],"ix":1},"s":{"a":0,"k":[159,159],"ix":3},"r":{"a":0,"k":0,"ix":6},"o":{"a":0,"k":100,"ix":7},"sk":{"a":0,"k":0,"ix":4},"sa":{"a":0,"k":0,"ix":5},"nm":"Transform"}],"nm":"Group 42","np":2,"cix":2,"ix":12,"mn":"ADBE Vector Group"},{"ty":"gr","it":[{"ind":0,"ty":"sh","ix":1,"ks":{"a":0,"k":{"i":[[0,-1.621],[1.621,0],[0,1.621],[-1.62,0]],"o":[[0,1.621],[-1.62,0],[0,-1.621],[1.621,0]],"v":[[2.935,-0.001],[-0.001,2.935],[-2.935,-0.001],[-0.001,-2.935]],"c":true}},"nm":"Path 1","mn":"ADBE Vector Shape - Group"},{"ty":"fl","c":{"a":0,"k":[1,1,1,1]},"o":{"a":0,"k":100},"r":1,"nm":"Fill 1","mn":"ADBE Vector Graphic - Fill"},{"ty":"tr","p":{"a":0,"k":[200.531,117.895],"ix":2},"a":{"a":0,"k":[0,0],"ix":1},"s":{"a":0,"k":[207,207],"ix":3},"r":{"a":0,"k":0,"ix":6},"o":{"a":0,"k":100,"ix":7},"sk":{"a":0,"k":0,"ix":4},"sa":{"a":0,"k":0,"ix":5},"nm":"Transform"}],"nm":"Group 49","np":2,"cix":2,"ix":13,"mn":"ADBE Vector Group"},{"ty":"gr","it":[{"ind":0,"ty":"sh","ix":1,"ks":{"a":0,"k":{"i":[[0,-4.142],[4.128,0],[0,4.142],[-4.128,0]],"o":[[0,4.142],[-4.128,0],[0,-4.142],[4.128,0]],"v":[[7.474,0],[0,7.5],[-7.474,0],[0,-7.5]],"c":true}},"nm":"Path 1","mn":"ADBE Vector Shape - Group"},{"ty":"fl","c":{"a":0,"k":[1,0.267,0.357,1]},"o":{"a":0,"k":100},"r":1,"nm":"Fill 1","mn":"ADBE Vector Graphic - Fill"},{"ty":"tr","p":{"a":0,"k":[200.532,117.894],"ix":2},"a":{"a":0,"k":[0,0],"ix":1},"s":{"a":0,"k":[159,159],"ix":3},"r":{"a":0,"k":0,"ix":6},"o":{"a":0,"k":100,"ix":7},"sk":{"a":0,"k":0,"ix":4},"sa":{"a":0,"k":0,"ix":5},"nm":"Transform"}],"nm":"Group 50","np":2,"cix":2,"ix":14,"mn":"ADBE Vector Group"},{"ty":"gr","it":[{"ind":0,"ty":"sh","ix":1,"ks":{"a":0,"k":{"i":[[0,-1.621],[1.621,0],[0,1.621],[-1.62,0]],"o":[[0,1.621],[-1.62,0],[0,-1.621],[1.621,0]],"v":[[2.935,-0.001],[-0.001,2.935],[-2.935,-0.001],[-0.001,-2.935]],"c":true}},"nm":"Path 1","mn":"ADBE Vector Shape - Group"},{"ty":"fl","c":{"a":0,"k":[1,1,1,1]},"o":{"a":0,"k":100},"r":1,"nm":"Fill 1","mn":"ADBE Vector Graphic - Fill"},{"ty":"tr","p":{"a":0,"k":[164.531,117.895],"ix":2},"a":{"a":0,"k":[0,0],"ix":1},"s":{"a":0,"k":[207,207],"ix":3},"r":{"a":0,"k":0,"ix":6},"o":{"a":0,"k":100,"ix":7},"sk":{"a":0,"k":0,"ix":4},"sa":{"a":0,"k":0,"ix":5},"nm":"Transform"}],"nm":"Group 53","np":2,"cix":2,"ix":15,"mn":"ADBE Vector Group"},{"ty":"gr","it":[{"ind":0,"ty":"sh","ix":1,"ks":{"a":0,"k":{"i":[[0,-4.142],[4.128,0],[0,4.142],[-4.128,0]],"o":[[0,4.142],[-4.128,0],[0,-4.142],[4.128,0]],"v":[[7.474,0],[0,7.5],[-7.474,0],[0,-7.5]],"c":true}},"nm":"Path 1","mn":"ADBE Vector Shape - Group"},{"ty":"fl","c":{"a":0,"k":[1,0.267,0.357,1]},"o":{"a":0,"k":100},"r":1,"nm":"Fill 1","mn":"ADBE Vector Graphic - Fill"},{"ty":"tr","p":{"a":0,"k":[164.532,117.894],"ix":2},"a":{"a":0,"k":[0,0],"ix":1},"s":{"a":0,"k":[159,159],"ix":3},"r":{"a":0,"k":0,"ix":6},"o":{"a":0,"k":100,"ix":7},"sk":{"a":0,"k":0,"ix":4},"sa":{"a":0,"k":0,"ix":5},"nm":"Transform"}],"nm":"Group 54","np":2,"cix":2,"ix":16,"mn":"ADBE Vector Group"},{"ty":"gr","it":[{"ind":0,"ty":"sh","ix":1,"ks":{"a":0,"k":{"i":[[0,-1.62],[1.621,0],[0,1.621],[-1.62,0]],"o":[[0,1.621],[-1.62,0],[0,-1.62],[1.621,0]],"v":[[2.935,0],[-0.001,2.935],[-2.935,0],[-0.001,-2.935]],"c":true}},"nm":"Path 1","mn":"ADBE Vector Shape - Group"},{"ty":"fl","c":{"a":0,"k":[1,1,1,1]},"o":{"a":0,"k":100},"r":1,"nm":"Fill 1","mn":"ADBE Vector Graphic - Fill"},{"ty":"tr","p":{"a":0,"k":[273.391,335.521],"ix":2},"a":{"a":0,"k":[0,0],"ix":1},"s":{"a":0,"k":[207,207],"ix":3},"r":{"a":0,"k":0,"ix":6},"o":{"a":0,"k":100,"ix":7},"sk":{"a":0,"k":0,"ix":4},"sa":{"a":0,"k":0,"ix":5},"nm":"Transform"}],"nm":"Group 67","np":2,"cix":2,"ix":17,"mn":"ADBE Vector Group"},{"ty":"gr","it":[{"ind":0,"ty":"sh","ix":1,"ks":{"a":0,"k":{"i":[[0,-4.142],[4.128,0],[0,4.143],[-4.128,0]],"o":[[0,4.143],[-4.128,0],[0,-4.142],[4.128,0]],"v":[[7.474,0],[0,7.5],[-7.474,0],[0,-7.5]],"c":true}},"nm":"Path 1","mn":"ADBE Vector Shape - Group"},{"ty":"fl","c":{"a":0,"k":[1,0.267,0.357,1]},"o":{"a":0,"k":100},"r":1,"nm":"Fill 1","mn":"ADBE Vector Graphic - Fill"},{"ty":"tr","p":{"a":0,"k":[273.391,335.521],"ix":2},"a":{"a":0,"k":[0,0],"ix":1},"s":{"a":0,"k":[159,159],"ix":3},"r":{"a":0,"k":0,"ix":6},"o":{"a":0,"k":100,"ix":7},"sk":{"a":0,"k":0,"ix":4},"sa":{"a":0,"k":0,"ix":5},"nm":"Transform"}],"nm":"Group 68","np":2,"cix":2,"ix":18,"mn":"ADBE Vector Group"},{"ty":"gr","it":[{"ind":0,"ty":"sh","ix":1,"ks":{"a":0,"k":{"i":[[0,-1.62],[1.621,0],[0,1.621],[-1.62,0]],"o":[[0,1.621],[-1.62,0],[0,-1.62],[1.621,0]],"v":[[2.935,0],[-0.001,2.935],[-2.935,0],[-0.001,-2.935]],"c":true}},"nm":"Path 1","mn":"ADBE Vector Shape - Group"},{"ty":"fl","c":{"a":0,"k":[1,1,1,1]},"o":{"a":0,"k":100},"r":1,"nm":"Fill 1","mn":"ADBE Vector Graphic - Fill"},{"ty":"tr","p":{"a":0,"k":[237.391,335.521],"ix":2},"a":{"a":0,"k":[0,0],"ix":1},"s":{"a":0,"k":[207,207],"ix":3},"r":{"a":0,"k":0,"ix":6},"o":{"a":0,"k":100,"ix":7},"sk":{"a":0,"k":0,"ix":4},"sa":{"a":0,"k":0,"ix":5},"nm":"Transform"}],"nm":"Group 71","np":2,"cix":2,"ix":19,"mn":"ADBE Vector Group"},{"ty":"gr","it":[{"ind":0,"ty":"sh","ix":1,"ks":{"a":0,"k":{"i":[[0,-4.142],[4.128,0],[0,4.143],[-4.128,0]],"o":[[0,4.143],[-4.128,0],[0,-4.142],[4.128,0]],"v":[[7.474,0],[0,7.5],[-7.474,0],[0,-7.5]],"c":true}},"nm":"Path 1","mn":"ADBE Vector Shape - Group"},{"ty":"fl","c":{"a":0,"k":[1,0.267,0.357,1]},"o":{"a":0,"k":100},"r":1,"nm":"Fill 1","mn":"ADBE Vector Graphic - Fill"},{"ty":"tr","p":{"a":0,"k":[237.391,335.521],"ix":2},"a":{"a":0,"k":[0,0],"ix":1},"s":{"a":0,"k":[159,159],"ix":3},"r":{"a":0,"k":0,"ix":6},"o":{"a":0,"k":100,"ix":7},"sk":{"a":0,"k":0,"ix":4},"sa":{"a":0,"k":0,"ix":5},"nm":"Transform"}],"nm":"Group 72","np":2,"cix":2,"ix":20,"mn":"ADBE Vector Group"},{"ty":"gr","it":[{"ind":0,"ty":"sh","ix":1,"ks":{"a":0,"k":{"i":[[0,-1.621],[1.622,0],[0,1.621],[-1.62,0]],"o":[[0,1.621],[-1.62,0],[0,-1.621],[1.622,0]],"v":[[2.935,0],[-0.001,2.935],[-2.935,0],[-0.001,-2.935]],"c":true}},"nm":"Path 1","mn":"ADBE Vector Shape - Group"},{"ty":"fl","c":{"a":0,"k":[1,1,1,1]},"o":{"a":0,"k":100},"r":1,"nm":"Fill 1","mn":"ADBE Vector Graphic - Fill"},{"ty":"tr","p":{"a":0,"k":[253.766,307.532],"ix":2},"a":{"a":0,"k":[0,0],"ix":1},"s":{"a":0,"k":[207,207],"ix":3},"r":{"a":0,"k":0,"ix":6},"o":{"a":0,"k":100,"ix":7},"sk":{"a":0,"k":0,"ix":4},"sa":{"a":0,"k":0,"ix":5},"nm":"Transform"}],"nm":"Group 79","np":2,"cix":2,"ix":21,"mn":"ADBE Vector Group"},{"ty":"gr","it":[{"ind":0,"ty":"sh","ix":1,"ks":{"a":0,"k":{"i":[[0,-4.143],[4.128,0],[0,4.143],[-4.128,0]],"o":[[0,4.143],[-4.128,0],[0,-4.143],[4.128,0]],"v":[[7.475,0],[-0.001,7.5],[-7.475,0],[-0.001,-7.5]],"c":true}},"nm":"Path 1","mn":"ADBE Vector Shape - Group"},{"ty":"fl","c":{"a":0,"k":[1,0.267,0.357,1]},"o":{"a":0,"k":100},"r":1,"nm":"Fill 1","mn":"ADBE Vector Graphic - Fill"},{"ty":"tr","p":{"a":0,"k":[253.766,307.532],"ix":2},"a":{"a":0,"k":[0,0],"ix":1},"s":{"a":0,"k":[159,159],"ix":3},"r":{"a":0,"k":0,"ix":6},"o":{"a":0,"k":100,"ix":7},"sk":{"a":0,"k":0,"ix":4},"sa":{"a":0,"k":0,"ix":5},"nm":"Transform"}],"nm":"Group 80","np":2,"cix":2,"ix":22,"mn":"ADBE Vector Group"},{"ty":"gr","it":[{"ind":0,"ty":"sh","ix":1,"ks":{"a":0,"k":{"i":[[0,-1.621],[1.622,0],[0,1.621],[-1.62,0]],"o":[[0,1.621],[-1.62,0],[0,-1.621],[1.622,0]],"v":[[2.935,0],[-0.001,2.935],[-2.935,0],[-0.001,-2.935]],"c":true}},"nm":"Path 1","mn":"ADBE Vector Shape - Group"},{"ty":"fl","c":{"a":0,"k":[1,1,1,1]},"o":{"a":0,"k":100},"r":1,"nm":"Fill 1","mn":"ADBE Vector Graphic - Fill"},{"ty":"tr","p":{"a":0,"k":[217.766,307.532],"ix":2},"a":{"a":0,"k":[0,0],"ix":1},"s":{"a":0,"k":[207,207],"ix":3},"r":{"a":0,"k":0,"ix":6},"o":{"a":0,"k":100,"ix":7},"sk":{"a":0,"k":0,"ix":4},"sa":{"a":0,"k":0,"ix":5},"nm":"Transform"}],"nm":"Group 83","np":2,"cix":2,"ix":23,"mn":"ADBE Vector Group"},{"ty":"gr","it":[{"ind":0,"ty":"sh","ix":1,"ks":{"a":0,"k":{"i":[[0,-4.143],[4.128,0],[0,4.143],[-4.128,0]],"o":[[0,4.143],[-4.128,0],[0,-4.143],[4.128,0]],"v":[[7.475,0],[-0.001,7.5],[-7.475,0],[-0.001,-7.5]],"c":true}},"nm":"Path 1","mn":"ADBE Vector Shape - Group"},{"ty":"fl","c":{"a":0,"k":[1,0.267,0.357,1]},"o":{"a":0,"k":100},"r":1,"nm":"Fill 1","mn":"ADBE Vector Graphic - Fill"},{"ty":"tr","p":{"a":0,"k":[217.766,307.532],"ix":2},"a":{"a":0,"k":[0,0],"ix":1},"s":{"a":0,"k":[159,159],"ix":3},"r":{"a":0,"k":0,"ix":6},"o":{"a":0,"k":100,"ix":7},"sk":{"a":0,"k":0,"ix":4},"sa":{"a":0,"k":0,"ix":5},"nm":"Transform"}],"nm":"Group 84","np":2,"cix":2,"ix":24,"mn":"ADBE Vector Group"},{"ty":"gr","it":[{"ind":0,"ty":"sh","ix":1,"ks":{"a":0,"k":{"i":[[0,-1.621],[1.621,0],[0,1.621],[-1.62,0]],"o":[[0,1.621],[-1.62,0],[0,-1.621],[1.621,0]],"v":[[2.935,0],[-0.001,2.935],[-2.935,0],[-0.001,-2.935]],"c":true}},"nm":"Path 1","mn":"ADBE Vector Shape - Group"},{"ty":"fl","c":{"a":0,"k":[1,1,1,1]},"o":{"a":0,"k":100},"r":1,"nm":"Fill 1","mn":"ADBE Vector Graphic - Fill"},{"ty":"tr","p":{"a":0,"k":[198.52,225.317],"ix":2},"a":{"a":0,"k":[0,0],"ix":1},"s":{"a":0,"k":[207,207],"ix":3},"r":{"a":0,"k":0,"ix":6},"o":{"a":0,"k":100,"ix":7},"sk":{"a":0,"k":0,"ix":4},"sa":{"a":0,"k":0,"ix":5},"nm":"Transform"}],"nm":"Group 85","np":2,"cix":2,"ix":25,"mn":"ADBE Vector Group"},{"ty":"gr","it":[{"ind":0,"ty":"sh","ix":1,"ks":{"a":0,"k":{"i":[[0,-4.142],[4.128,0],[0,4.142],[-4.128,0]],"o":[[0,4.142],[-4.128,0],[0,-4.142],[4.128,0]],"v":[[7.475,0],[-0.001,7.5],[-7.475,0],[-0.001,-7.5]],"c":true}},"nm":"Path 1","mn":"ADBE Vector Shape - Group"},{"ty":"fl","c":{"a":0,"k":[1,0.267,0.357,1]},"o":{"a":0,"k":100},"r":1,"nm":"Fill 1","mn":"ADBE Vector Graphic - Fill"},{"ty":"tr","p":{"a":0,"k":[198.52,225.317],"ix":2},"a":{"a":0,"k":[0,0],"ix":1},"s":{"a":0,"k":[159,159],"ix":3},"r":{"a":0,"k":0,"ix":6},"o":{"a":0,"k":100,"ix":7},"sk":{"a":0,"k":0,"ix":4},"sa":{"a":0,"k":0,"ix":5},"nm":"Transform"}],"nm":"Group 86","np":2,"cix":2,"ix":26,"mn":"ADBE Vector Group"},{"ty":"gr","it":[{"ind":0,"ty":"sh","ix":1,"ks":{"a":0,"k":{"i":[[0,-1.621],[1.621,0],[0,1.621],[-1.62,0]],"o":[[0,1.621],[-1.62,0],[0,-1.621],[1.621,0]],"v":[[2.935,0],[-0.001,2.935],[-2.935,0],[-0.001,-2.935]],"c":true}},"nm":"Path 1","mn":"ADBE Vector Shape - Group"},{"ty":"fl","c":{"a":0,"k":[1,1,1,1]},"o":{"a":0,"k":100},"r":1,"nm":"Fill 1","mn":"ADBE Vector Graphic - Fill"},{"ty":"tr","p":{"a":0,"k":[162.52,225.317],"ix":2},"a":{"a":0,"k":[0,0],"ix":1},"s":{"a":0,"k":[207,207],"ix":3},"r":{"a":0,"k":0,"ix":6},"o":{"a":0,"k":100,"ix":7},"sk":{"a":0,"k":0,"ix":4},"sa":{"a":0,"k":0,"ix":5},"nm":"Transform"}],"nm":"Group 89","np":2,"cix":2,"ix":27,"mn":"ADBE Vector Group"},{"ty":"gr","it":[{"ind":0,"ty":"sh","ix":1,"ks":{"a":0,"k":{"i":[[0,-4.142],[4.128,0],[0,4.142],[-4.128,0]],"o":[[0,4.142],[-4.128,0],[0,-4.142],[4.128,0]],"v":[[7.475,0],[-0.001,7.5],[-7.475,0],[-0.001,-7.5]],"c":true}},"nm":"Path 1","mn":"ADBE Vector Shape - Group"},{"ty":"fl","c":{"a":0,"k":[1,0.267,0.357,1]},"o":{"a":0,"k":100},"r":1,"nm":"Fill 1","mn":"ADBE Vector Graphic - Fill"},{"ty":"tr","p":{"a":0,"k":[162.52,225.317],"ix":2},"a":{"a":0,"k":[0,0],"ix":1},"s":{"a":0,"k":[159,159],"ix":3},"r":{"a":0,"k":0,"ix":6},"o":{"a":0,"k":100,"ix":7},"sk":{"a":0,"k":0,"ix":4},"sa":{"a":0,"k":0,"ix":5},"nm":"Transform"}],"nm":"Group 90","np":2,"cix":2,"ix":28,"mn":"ADBE Vector Group"},{"ty":"gr","it":[{"ind":0,"ty":"sh","ix":1,"ks":{"a":0,"k":{"i":[[0,-1.621],[1.621,0],[0,1.621],[-1.62,0]],"o":[[0,1.621],[-1.62,0],[0,-1.621],[1.621,0]],"v":[[2.935,0],[-0.001,2.935],[-2.935,0],[-0.001,-2.935]],"c":true}},"nm":"Path 1","mn":"ADBE Vector Shape - Group"},{"ty":"fl","c":{"a":0,"k":[1,1,1,1]},"o":{"a":0,"k":100},"r":1,"nm":"Fill 1","mn":"ADBE Vector Graphic - Fill"},{"ty":"tr","p":{"a":0,"k":[235.741,280.804],"ix":2},"a":{"a":0,"k":[0,0],"ix":1},"s":{"a":0,"k":[207,207],"ix":3},"r":{"a":0,"k":0,"ix":6},"o":{"a":0,"k":100,"ix":7},"sk":{"a":0,"k":0,"ix":4},"sa":{"a":0,"k":0,"ix":5},"nm":"Transform"}],"nm":"Group 97","np":2,"cix":2,"ix":29,"mn":"ADBE Vector Group"},{"ty":"gr","it":[{"ind":0,"ty":"sh","ix":1,"ks":{"a":0,"k":{"i":[[0,-4.142],[4.128,0],[0,4.143],[-4.128,0]],"o":[[0,4.143],[-4.128,0],[0,-4.142],[4.128,0]],"v":[[7.475,0],[0,7.5],[-7.475,0],[0,-7.5]],"c":true}},"nm":"Path 1","mn":"ADBE Vector Shape - Group"},{"ty":"fl","c":{"a":0,"k":[1,0.267,0.357,1]},"o":{"a":0,"k":100},"r":1,"nm":"Fill 1","mn":"ADBE Vector Graphic - Fill"},{"ty":"tr","p":{"a":0,"k":[235.741,280.804],"ix":2},"a":{"a":0,"k":[0,0],"ix":1},"s":{"a":0,"k":[159,159],"ix":3},"r":{"a":0,"k":0,"ix":6},"o":{"a":0,"k":100,"ix":7},"sk":{"a":0,"k":0,"ix":4},"sa":{"a":0,"k":0,"ix":5},"nm":"Transform"}],"nm":"Group 98","np":2,"cix":2,"ix":30,"mn":"ADBE Vector Group"},{"ty":"gr","it":[{"ind":0,"ty":"sh","ix":1,"ks":{"a":0,"k":{"i":[[0,-1.621],[1.621,0],[0,1.621],[-1.62,0]],"o":[[0,1.621],[-1.62,0],[0,-1.621],[1.621,0]],"v":[[2.935,0],[-0.001,2.935],[-2.935,0],[-0.001,-2.935]],"c":true}},"nm":"Path 1","mn":"ADBE Vector Shape - Group"},{"ty":"fl","c":{"a":0,"k":[1,1,1,1]},"o":{"a":0,"k":100},"r":1,"nm":"Fill 1","mn":"ADBE Vector Graphic - Fill"},{"ty":"tr","p":{"a":0,"k":[199.741,280.804],"ix":2},"a":{"a":0,"k":[0,0],"ix":1},"s":{"a":0,"k":[207,207],"ix":3},"r":{"a":0,"k":0,"ix":6},"o":{"a":0,"k":100,"ix":7},"sk":{"a":0,"k":0,"ix":4},"sa":{"a":0,"k":0,"ix":5},"nm":"Transform"}],"nm":"Group 101","np":2,"cix":2,"ix":31,"mn":"ADBE Vector Group"},{"ty":"gr","it":[{"ind":0,"ty":"sh","ix":1,"ks":{"a":0,"k":{"i":[[0,-4.142],[4.128,0],[0,4.143],[-4.128,0]],"o":[[0,4.143],[-4.128,0],[0,-4.142],[4.128,0]],"v":[[7.475,0],[0,7.5],[-7.475,0],[0,-7.5]],"c":true}},"nm":"Path 1","mn":"ADBE Vector Shape - Group"},{"ty":"fl","c":{"a":0,"k":[1,0.267,0.357,1]},"o":{"a":0,"k":100},"r":1,"nm":"Fill 1","mn":"ADBE Vector Graphic - Fill"},{"ty":"tr","p":{"a":0,"k":[199.741,280.804],"ix":2},"a":{"a":0,"k":[0,0],"ix":1},"s":{"a":0,"k":[159,159],"ix":3},"r":{"a":0,"k":0,"ix":6},"o":{"a":0,"k":100,"ix":7},"sk":{"a":0,"k":0,"ix":4},"sa":{"a":0,"k":0,"ix":5},"nm":"Transform"}],"nm":"Group 102","np":2,"cix":2,"ix":32,"mn":"ADBE Vector Group"},{"ty":"gr","it":[{"ind":0,"ty":"sh","ix":1,"ks":{"a":0,"k":{"i":[[0,-1.62],[1.622,0],[0,1.621],[-1.62,0]],"o":[[0,1.621],[-1.62,0],[0,-1.62],[1.622,0]],"v":[[2.935,0],[-0.001,2.935],[-2.935,0],[-0.001,-2.935]],"c":true}},"nm":"Path 1","mn":"ADBE Vector Shape - Group"},{"ty":"fl","c":{"a":0,"k":[1,1,1,1]},"o":{"a":0,"k":100},"r":1,"nm":"Fill 1","mn":"ADBE Vector Graphic - Fill"},{"ty":"tr","p":{"a":0,"k":[217.766,252.524],"ix":2},"a":{"a":0,"k":[0,0],"ix":1},"s":{"a":0,"k":[207,207],"ix":3},"r":{"a":0,"k":0,"ix":6},"o":{"a":0,"k":100,"ix":7},"sk":{"a":0,"k":0,"ix":4},"sa":{"a":0,"k":0,"ix":5},"nm":"Transform"}],"nm":"Group 109","np":2,"cix":2,"ix":33,"mn":"ADBE Vector Group"},{"ty":"gr","it":[{"ind":0,"ty":"sh","ix":1,"ks":{"a":0,"k":{"i":[[0,-4.142],[4.128,0],[0,4.143],[-4.128,0]],"o":[[0,4.143],[-4.128,0],[0,-4.142],[4.128,0]],"v":[[7.475,0],[-0.001,7.5],[-7.475,0],[-0.001,-7.5]],"c":true}},"nm":"Path 1","mn":"ADBE Vector Shape - Group"},{"ty":"fl","c":{"a":0,"k":[1,0.267,0.357,1]},"o":{"a":0,"k":100},"r":1,"nm":"Fill 1","mn":"ADBE Vector Graphic - Fill"},{"ty":"tr","p":{"a":0,"k":[217.766,252.524],"ix":2},"a":{"a":0,"k":[0,0],"ix":1},"s":{"a":0,"k":[159,159],"ix":3},"r":{"a":0,"k":0,"ix":6},"o":{"a":0,"k":100,"ix":7},"sk":{"a":0,"k":0,"ix":4},"sa":{"a":0,"k":0,"ix":5},"nm":"Transform"}],"nm":"Group 110","np":2,"cix":2,"ix":34,"mn":"ADBE Vector Group"},{"ty":"gr","it":[{"ind":0,"ty":"sh","ix":1,"ks":{"a":0,"k":{"i":[[0,-1.62],[1.622,0],[0,1.621],[-1.62,0]],"o":[[0,1.621],[-1.62,0],[0,-1.62],[1.622,0]],"v":[[2.935,0],[-0.001,2.935],[-2.935,0],[-0.001,-2.935]],"c":true}},"nm":"Path 1","mn":"ADBE Vector Shape - Group"},{"ty":"fl","c":{"a":0,"k":[1,1,1,1]},"o":{"a":0,"k":100},"r":1,"nm":"Fill 1","mn":"ADBE Vector Graphic - Fill"},{"ty":"tr","p":{"a":0,"k":[181.766,252.524],"ix":2},"a":{"a":0,"k":[0,0],"ix":1},"s":{"a":0,"k":[207,207],"ix":3},"r":{"a":0,"k":0,"ix":6},"o":{"a":0,"k":100,"ix":7},"sk":{"a":0,"k":0,"ix":4},"sa":{"a":0,"k":0,"ix":5},"nm":"Transform"}],"nm":"Group 113","np":2,"cix":2,"ix":35,"mn":"ADBE Vector Group"},{"ty":"gr","it":[{"ind":0,"ty":"sh","ix":1,"ks":{"a":0,"k":{"i":[[0,-4.142],[4.128,0],[0,4.143],[-4.128,0]],"o":[[0,4.143],[-4.128,0],[0,-4.142],[4.128,0]],"v":[[7.475,0],[-0.001,7.5],[-7.475,0],[-0.001,-7.5]],"c":true}},"nm":"Path 1","mn":"ADBE Vector Shape - Group"},{"ty":"fl","c":{"a":0,"k":[1,0.267,0.357,1]},"o":{"a":0,"k":100},"r":1,"nm":"Fill 1","mn":"ADBE Vector Graphic - Fill"},{"ty":"tr","p":{"a":0,"k":[181.766,252.524],"ix":2},"a":{"a":0,"k":[0,0],"ix":1},"s":{"a":0,"k":[159,159],"ix":3},"r":{"a":0,"k":0,"ix":6},"o":{"a":0,"k":100,"ix":7},"sk":{"a":0,"k":0,"ix":4},"sa":{"a":0,"k":0,"ix":5},"nm":"Transform"}],"nm":"Group 114","np":2,"cix":2,"ix":36,"mn":"ADBE Vector Group"},{"ty":"gr","it":[{"ind":0,"ty":"sh","ix":1,"ks":{"a":0,"k":{"i":[[0,-1.621],[1.621,0],[0,1.62],[-1.621,0]],"o":[[0,1.62],[-1.621,0],[0,-1.621],[1.621,0]],"v":[[2.935,0],[0.001,2.935],[-2.935,0],[0.001,-2.935]],"c":true}},"nm":"Path 1","mn":"ADBE Vector Shape - Group"},{"ty":"fl","c":{"a":0,"k":[1,1,1,1]},"o":{"a":0,"k":100},"r":1,"nm":"Fill 1","mn":"ADBE Vector Graphic - Fill"},{"ty":"tr","p":{"a":0,"k":[52.01,334.94],"ix":2},"a":{"a":0,"k":[0,0],"ix":1},"s":{"a":0,"k":[207,207],"ix":3},"r":{"a":0,"k":0,"ix":6},"o":{"a":0,"k":100,"ix":7},"sk":{"a":0,"k":0,"ix":4},"sa":{"a":0,"k":0,"ix":5},"nm":"Transform"}],"nm":"Group 127","np":2,"cix":2,"ix":37,"mn":"ADBE Vector Group"},{"ty":"gr","it":[{"ind":0,"ty":"sh","ix":1,"ks":{"a":0,"k":{"i":[[0,-4.143],[4.128,0],[0,4.142],[-4.128,0]],"o":[[0,4.142],[-4.128,0],[0,-4.143],[4.128,0]],"v":[[7.475,0],[0,7.5],[-7.475,0],[0,-7.5]],"c":true}},"nm":"Path 1","mn":"ADBE Vector Shape - Group"},{"ty":"fl","c":{"a":0,"k":[1,0.267,0.357,1]},"o":{"a":0,"k":100},"r":1,"nm":"Fill 1","mn":"ADBE Vector Graphic - Fill"},{"ty":"tr","p":{"a":0,"k":[52.01,334.94],"ix":2},"a":{"a":0,"k":[0,0],"ix":1},"s":{"a":0,"k":[159,159],"ix":3},"r":{"a":0,"k":0,"ix":6},"o":{"a":0,"k":100,"ix":7},"sk":{"a":0,"k":0,"ix":4},"sa":{"a":0,"k":0,"ix":5},"nm":"Transform"}],"nm":"Group 128","np":2,"cix":2,"ix":38,"mn":"ADBE Vector Group"},{"ty":"gr","it":[{"ind":0,"ty":"sh","ix":1,"ks":{"a":0,"k":{"i":[[0,-1.621],[1.621,0],[0,1.62],[-1.621,0]],"o":[[0,1.62],[-1.621,0],[0,-1.621],[1.621,0]],"v":[[2.935,0],[0.001,2.935],[-2.935,0],[0.001,-2.935]],"c":true}},"nm":"Path 1","mn":"ADBE Vector Shape - Group"},{"ty":"fl","c":{"a":0,"k":[1,1,1,1]},"o":{"a":0,"k":100},"r":1,"nm":"Fill 1","mn":"ADBE Vector Graphic - Fill"},{"ty":"tr","p":{"a":0,"k":[16.01,334.94],"ix":2},"a":{"a":0,"k":[0,0],"ix":1},"s":{"a":0,"k":[207,207],"ix":3},"r":{"a":0,"k":0,"ix":6},"o":{"a":0,"k":100,"ix":7},"sk":{"a":0,"k":0,"ix":4},"sa":{"a":0,"k":0,"ix":5},"nm":"Transform"}],"nm":"Group 131","np":2,"cix":2,"ix":39,"mn":"ADBE Vector Group"},{"ty":"gr","it":[{"ind":0,"ty":"sh","ix":1,"ks":{"a":0,"k":{"i":[[0,-4.143],[4.128,0],[0,4.142],[-4.128,0]],"o":[[0,4.142],[-4.128,0],[0,-4.143],[4.128,0]],"v":[[7.475,0],[0,7.5],[-7.475,0],[0,-7.5]],"c":true}},"nm":"Path 1","mn":"ADBE Vector Shape - Group"},{"ty":"fl","c":{"a":0,"k":[1,0.267,0.357,1]},"o":{"a":0,"k":100},"r":1,"nm":"Fill 1","mn":"ADBE Vector Graphic - Fill"},{"ty":"tr","p":{"a":0,"k":[16.01,334.94],"ix":2},"a":{"a":0,"k":[0,0],"ix":1},"s":{"a":0,"k":[159,159],"ix":3},"r":{"a":0,"k":0,"ix":6},"o":{"a":0,"k":100,"ix":7},"sk":{"a":0,"k":0,"ix":4},"sa":{"a":0,"k":0,"ix":5},"nm":"Transform"}],"nm":"Group 132","np":2,"cix":2,"ix":40,"mn":"ADBE Vector Group"},{"ty":"gr","it":[{"ind":0,"ty":"sh","ix":1,"ks":{"a":0,"k":{"i":[[0,-1.621],[1.621,0],[0,1.62],[-1.62,0]],"o":[[0,1.62],[-1.62,0],[0,-1.621],[1.621,0]],"v":[[2.935,0],[-0.001,2.935],[-2.935,0],[-0.001,-2.935]],"c":true}},"nm":"Path 1","mn":"ADBE Vector Shape - Group"},{"ty":"fl","c":{"a":0,"k":[1,1,1,1]},"o":{"a":0,"k":100},"r":1,"nm":"Fill 1","mn":"ADBE Vector Graphic - Fill"},{"ty":"tr","p":{"a":0,"k":[72.025,307.867],"ix":2},"a":{"a":0,"k":[0,0],"ix":1},"s":{"a":0,"k":[207,207],"ix":3},"r":{"a":0,"k":0,"ix":6},"o":{"a":0,"k":100,"ix":7},"sk":{"a":0,"k":0,"ix":4},"sa":{"a":0,"k":0,"ix":5},"nm":"Transform"}],"nm":"Group 139","np":2,"cix":2,"ix":41,"mn":"ADBE Vector Group"},{"ty":"gr","it":[{"ind":0,"ty":"sh","ix":1,"ks":{"a":0,"k":{"i":[[0,-4.143],[4.128,0],[0,4.142],[-4.128,0]],"o":[[0,4.142],[-4.128,0],[0,-4.143],[4.128,0]],"v":[[7.475,0],[0,7.5],[-7.475,0],[0,-7.5]],"c":true}},"nm":"Path 1","mn":"ADBE Vector Shape - Group"},{"ty":"fl","c":{"a":0,"k":[1,0.267,0.357,1]},"o":{"a":0,"k":100},"r":1,"nm":"Fill 1","mn":"ADBE Vector Graphic - Fill"},{"ty":"tr","p":{"a":0,"k":[72.025,307.867],"ix":2},"a":{"a":0,"k":[0,0],"ix":1},"s":{"a":0,"k":[159,159],"ix":3},"r":{"a":0,"k":0,"ix":6},"o":{"a":0,"k":100,"ix":7},"sk":{"a":0,"k":0,"ix":4},"sa":{"a":0,"k":0,"ix":5},"nm":"Transform"}],"nm":"Group 140","np":2,"cix":2,"ix":42,"mn":"ADBE Vector Group"},{"ty":"gr","it":[{"ind":0,"ty":"sh","ix":1,"ks":{"a":0,"k":{"i":[[0,-1.621],[1.621,0],[0,1.62],[-1.62,0]],"o":[[0,1.62],[-1.62,0],[0,-1.621],[1.621,0]],"v":[[2.935,0],[-0.001,2.935],[-2.935,0],[-0.001,-2.935]],"c":true}},"nm":"Path 1","mn":"ADBE Vector Shape - Group"},{"ty":"fl","c":{"a":0,"k":[1,1,1,1]},"o":{"a":0,"k":100},"r":1,"nm":"Fill 1","mn":"ADBE Vector Graphic - Fill"},{"ty":"tr","p":{"a":0,"k":[36.025,307.867],"ix":2},"a":{"a":0,"k":[0,0],"ix":1},"s":{"a":0,"k":[207,207],"ix":3},"r":{"a":0,"k":0,"ix":6},"o":{"a":0,"k":100,"ix":7},"sk":{"a":0,"k":0,"ix":4},"sa":{"a":0,"k":0,"ix":5},"nm":"Transform"}],"nm":"Group 143","np":2,"cix":2,"ix":43,"mn":"ADBE Vector Group"},{"ty":"gr","it":[{"ind":0,"ty":"sh","ix":1,"ks":{"a":0,"k":{"i":[[0,-4.143],[4.128,0],[0,4.142],[-4.128,0]],"o":[[0,4.142],[-4.128,0],[0,-4.143],[4.128,0]],"v":[[7.475,0],[0,7.5],[-7.475,0],[0,-7.5]],"c":true}},"nm":"Path 1","mn":"ADBE Vector Shape - Group"},{"ty":"fl","c":{"a":0,"k":[1,0.267,0.357,1]},"o":{"a":0,"k":100},"r":1,"nm":"Fill 1","mn":"ADBE Vector Graphic - Fill"},{"ty":"tr","p":{"a":0,"k":[36.025,307.867],"ix":2},"a":{"a":0,"k":[0,0],"ix":1},"s":{"a":0,"k":[159,159],"ix":3},"r":{"a":0,"k":0,"ix":6},"o":{"a":0,"k":100,"ix":7},"sk":{"a":0,"k":0,"ix":4},"sa":{"a":0,"k":0,"ix":5},"nm":"Transform"}],"nm":"Group 144","np":2,"cix":2,"ix":44,"mn":"ADBE Vector Group"},{"ty":"gr","it":[{"ind":0,"ty":"sh","ix":1,"ks":{"a":0,"k":{"i":[[0,-1.62],[1.622,0],[0,1.621],[-1.62,0]],"o":[[0,1.621],[-1.62,0],[0,-1.62],[1.622,0]],"v":[[2.935,0],[-0.001,2.935],[-2.935,0],[-0.001,-2.935]],"c":true}},"nm":"Path 1","mn":"ADBE Vector Shape - Group"},{"ty":"fl","c":{"a":0,"k":[1,1,1,1]},"o":{"a":0,"k":100},"r":1,"nm":"Fill 1","mn":"ADBE Vector Graphic - Fill"},{"ty":"tr","p":{"a":0,"k":[89.973,280.137],"ix":2},"a":{"a":0,"k":[0,0],"ix":1},"s":{"a":0,"k":[207,207],"ix":3},"r":{"a":0,"k":0,"ix":6},"o":{"a":0,"k":100,"ix":7},"sk":{"a":0,"k":0,"ix":4},"sa":{"a":0,"k":0,"ix":5},"nm":"Transform"}],"nm":"Group 151","np":2,"cix":2,"ix":45,"mn":"ADBE Vector Group"},{"ty":"gr","it":[{"ind":0,"ty":"sh","ix":1,"ks":{"a":0,"k":{"i":[[0,-4.142],[4.128,0],[0,4.143],[-4.128,0]],"o":[[0,4.143],[-4.128,0],[0,-4.142],[4.128,0]],"v":[[7.475,0],[-0.001,7.5],[-7.475,0],[-0.001,-7.5]],"c":true}},"nm":"Path 1","mn":"ADBE Vector Shape - Group"},{"ty":"fl","c":{"a":0,"k":[1,0.267,0.357,1]},"o":{"a":0,"k":100},"r":1,"nm":"Fill 1","mn":"ADBE Vector Graphic - Fill"},{"ty":"tr","p":{"a":0,"k":[89.973,280.137],"ix":2},"a":{"a":0,"k":[0,0],"ix":1},"s":{"a":0,"k":[159,159],"ix":3},"r":{"a":0,"k":0,"ix":6},"o":{"a":0,"k":100,"ix":7},"sk":{"a":0,"k":0,"ix":4},"sa":{"a":0,"k":0,"ix":5},"nm":"Transform"}],"nm":"Group 152","np":2,"cix":2,"ix":46,"mn":"ADBE Vector Group"},{"ty":"gr","it":[{"ind":0,"ty":"sh","ix":1,"ks":{"a":0,"k":{"i":[[0,-1.62],[1.622,0],[0,1.621],[-1.62,0]],"o":[[0,1.621],[-1.62,0],[0,-1.62],[1.622,0]],"v":[[2.935,0],[-0.001,2.935],[-2.935,0],[-0.001,-2.935]],"c":true}},"nm":"Path 1","mn":"ADBE Vector Shape - Group"},{"ty":"fl","c":{"a":0,"k":[1,1,1,1]},"o":{"a":0,"k":100},"r":1,"nm":"Fill 1","mn":"ADBE Vector Graphic - Fill"},{"ty":"tr","p":{"a":0,"k":[53.973,280.137],"ix":2},"a":{"a":0,"k":[0,0],"ix":1},"s":{"a":0,"k":[207,207],"ix":3},"r":{"a":0,"k":0,"ix":6},"o":{"a":0,"k":100,"ix":7},"sk":{"a":0,"k":0,"ix":4},"sa":{"a":0,"k":0,"ix":5},"nm":"Transform"}],"nm":"Group 155","np":2,"cix":2,"ix":47,"mn":"ADBE Vector Group"},{"ty":"gr","it":[{"ind":0,"ty":"sh","ix":1,"ks":{"a":0,"k":{"i":[[0,-4.142],[4.128,0],[0,4.143],[-4.128,0]],"o":[[0,4.143],[-4.128,0],[0,-4.142],[4.128,0]],"v":[[7.475,0],[-0.001,7.5],[-7.475,0],[-0.001,-7.5]],"c":true}},"nm":"Path 1","mn":"ADBE Vector Shape - Group"},{"ty":"fl","c":{"a":0,"k":[1,0.267,0.357,1]},"o":{"a":0,"k":100},"r":1,"nm":"Fill 1","mn":"ADBE Vector Graphic - Fill"},{"ty":"tr","p":{"a":0,"k":[53.973,280.137],"ix":2},"a":{"a":0,"k":[0,0],"ix":1},"s":{"a":0,"k":[159,159],"ix":3},"r":{"a":0,"k":0,"ix":6},"o":{"a":0,"k":100,"ix":7},"sk":{"a":0,"k":0,"ix":4},"sa":{"a":0,"k":0,"ix":5},"nm":"Transform"}],"nm":"Group 156","np":2,"cix":2,"ix":48,"mn":"ADBE Vector Group"},{"ty":"gr","it":[{"ind":0,"ty":"sh","ix":1,"ks":{"a":0,"k":{"i":[[0,-1.62],[1.622,0],[0,1.621],[-1.62,0]],"o":[[0,1.621],[-1.62,0],[0,-1.62],[1.622,0]],"v":[[2.935,0],[-0.001,2.935],[-2.935,0],[-0.001,-2.935]],"c":true}},"nm":"Path 1","mn":"ADBE Vector Shape - Group"},{"ty":"fl","c":{"a":0,"k":[1,1,1,1]},"o":{"a":0,"k":100},"r":1,"nm":"Fill 1","mn":"ADBE Vector Graphic - Fill"},{"ty":"tr","p":{"a":0,"k":[106.973,252.524],"ix":2},"a":{"a":0,"k":[0,0],"ix":1},"s":{"a":0,"k":[207,207],"ix":3},"r":{"a":0,"k":0,"ix":6},"o":{"a":0,"k":100,"ix":7},"sk":{"a":0,"k":0,"ix":4},"sa":{"a":0,"k":0,"ix":5},"nm":"Transform"}],"nm":"Group 163","np":2,"cix":2,"ix":49,"mn":"ADBE Vector Group"},{"ty":"gr","it":[{"ind":0,"ty":"sh","ix":1,"ks":{"a":0,"k":{"i":[[0,-4.142],[4.128,0],[0,4.143],[-4.128,0]],"o":[[0,4.143],[-4.128,0],[0,-4.142],[4.128,0]],"v":[[7.475,0],[-0.001,7.5],[-7.475,0],[-0.001,-7.5]],"c":true}},"nm":"Path 1","mn":"ADBE Vector Shape - Group"},{"ty":"fl","c":{"a":0,"k":[1,0.267,0.357,1]},"o":{"a":0,"k":100},"r":1,"nm":"Fill 1","mn":"ADBE Vector Graphic - Fill"},{"ty":"tr","p":{"a":0,"k":[106.973,252.524],"ix":2},"a":{"a":0,"k":[0,0],"ix":1},"s":{"a":0,"k":[159,159],"ix":3},"r":{"a":0,"k":0,"ix":6},"o":{"a":0,"k":100,"ix":7},"sk":{"a":0,"k":0,"ix":4},"sa":{"a":0,"k":0,"ix":5},"nm":"Transform"}],"nm":"Group 164","np":2,"cix":2,"ix":50,"mn":"ADBE Vector Group"},{"ty":"gr","it":[{"ind":0,"ty":"sh","ix":1,"ks":{"a":0,"k":{"i":[[0,-1.62],[1.622,0],[0,1.621],[-1.62,0]],"o":[[0,1.621],[-1.62,0],[0,-1.62],[1.622,0]],"v":[[2.935,0],[-0.001,2.935],[-2.935,0],[-0.001,-2.935]],"c":true}},"nm":"Path 1","mn":"ADBE Vector Shape - Group"},{"ty":"fl","c":{"a":0,"k":[1,1,1,1]},"o":{"a":0,"k":100},"r":1,"nm":"Fill 1","mn":"ADBE Vector Graphic - Fill"},{"ty":"tr","p":{"a":0,"k":[70.973,252.524],"ix":2},"a":{"a":0,"k":[0,0],"ix":1},"s":{"a":0,"k":[207,207],"ix":3},"r":{"a":0,"k":0,"ix":6},"o":{"a":0,"k":100,"ix":7},"sk":{"a":0,"k":0,"ix":4},"sa":{"a":0,"k":0,"ix":5},"nm":"Transform"}],"nm":"Group 167","np":2,"cix":2,"ix":51,"mn":"ADBE Vector Group"},{"ty":"gr","it":[{"ind":0,"ty":"sh","ix":1,"ks":{"a":0,"k":{"i":[[0,-4.142],[4.128,0],[0,4.143],[-4.128,0]],"o":[[0,4.143],[-4.128,0],[0,-4.142],[4.128,0]],"v":[[7.475,0],[-0.001,7.5],[-7.475,0],[-0.001,-7.5]],"c":true}},"nm":"Path 1","mn":"ADBE Vector Shape - Group"},{"ty":"fl","c":{"a":0,"k":[1,0.267,0.357,1]},"o":{"a":0,"k":100},"r":1,"nm":"Fill 1","mn":"ADBE Vector Graphic - Fill"},{"ty":"tr","p":{"a":0,"k":[70.973,252.524],"ix":2},"a":{"a":0,"k":[0,0],"ix":1},"s":{"a":0,"k":[159,159],"ix":3},"r":{"a":0,"k":0,"ix":6},"o":{"a":0,"k":100,"ix":7},"sk":{"a":0,"k":0,"ix":4},"sa":{"a":0,"k":0,"ix":5},"nm":"Transform"}],"nm":"Group 168","np":2,"cix":2,"ix":52,"mn":"ADBE Vector Group"},{"ty":"gr","it":[{"ind":0,"ty":"sh","ix":1,"ks":{"a":0,"k":{"i":[[0,-1.621],[1.622,0],[0,1.621],[-1.62,0]],"o":[[0,1.621],[-1.62,0],[0,-1.621],[1.622,0]],"v":[[2.935,0],[-0.001,2.935],[-2.935,0],[-0.001,-2.935]],"c":true}},"nm":"Path 1","mn":"ADBE Vector Shape - Group"},{"ty":"fl","c":{"a":0,"k":[1,1,1,1]},"o":{"a":0,"k":100},"r":1,"nm":"Fill 1","mn":"ADBE Vector Graphic - Fill"},{"ty":"tr","p":{"a":0,"k":[126.004,225.317],"ix":2},"a":{"a":0,"k":[0,0],"ix":1},"s":{"a":0,"k":[207,207],"ix":3},"r":{"a":0,"k":0,"ix":6},"o":{"a":0,"k":100,"ix":7},"sk":{"a":0,"k":0,"ix":4},"sa":{"a":0,"k":0,"ix":5},"nm":"Transform"}],"nm":"Group 175","np":2,"cix":2,"ix":53,"mn":"ADBE Vector Group"},{"ty":"gr","it":[{"ind":0,"ty":"sh","ix":1,"ks":{"a":0,"k":{"i":[[0,-4.142],[4.128,0],[0,4.142],[-4.128,0]],"o":[[0,4.142],[-4.128,0],[0,-4.142],[4.128,0]],"v":[[7.475,0],[-0.001,7.5],[-7.475,0],[-0.001,-7.5]],"c":true}},"nm":"Path 1","mn":"ADBE Vector Shape - Group"},{"ty":"fl","c":{"a":0,"k":[1,0.267,0.357,1]},"o":{"a":0,"k":100},"r":1,"nm":"Fill 1","mn":"ADBE Vector Graphic - Fill"},{"ty":"tr","p":{"a":0,"k":[126.004,225.317],"ix":2},"a":{"a":0,"k":[0,0],"ix":1},"s":{"a":0,"k":[159,159],"ix":3},"r":{"a":0,"k":0,"ix":6},"o":{"a":0,"k":100,"ix":7},"sk":{"a":0,"k":0,"ix":4},"sa":{"a":0,"k":0,"ix":5},"nm":"Transform"}],"nm":"Group 176","np":2,"cix":2,"ix":54,"mn":"ADBE Vector Group"},{"ty":"gr","it":[{"ind":0,"ty":"sh","ix":1,"ks":{"a":0,"k":{"i":[[0,-1.621],[1.622,0],[0,1.621],[-1.62,0]],"o":[[0,1.621],[-1.62,0],[0,-1.621],[1.622,0]],"v":[[2.935,0],[-0.001,2.935],[-2.935,0],[-0.001,-2.935]],"c":true}},"nm":"Path 1","mn":"ADBE Vector Shape - Group"},{"ty":"fl","c":{"a":0,"k":[1,1,1,1]},"o":{"a":0,"k":100},"r":1,"nm":"Fill 1","mn":"ADBE Vector Graphic - Fill"},{"ty":"tr","p":{"a":0,"k":[90.004,225.317],"ix":2},"a":{"a":0,"k":[0,0],"ix":1},"s":{"a":0,"k":[207,207],"ix":3},"r":{"a":0,"k":0,"ix":6},"o":{"a":0,"k":100,"ix":7},"sk":{"a":0,"k":0,"ix":4},"sa":{"a":0,"k":0,"ix":5},"nm":"Transform"}],"nm":"Group 179","np":2,"cix":2,"ix":55,"mn":"ADBE Vector Group"},{"ty":"gr","it":[{"ind":0,"ty":"sh","ix":1,"ks":{"a":0,"k":{"i":[[0,-4.142],[4.128,0],[0,4.142],[-4.128,0]],"o":[[0,4.142],[-4.128,0],[0,-4.142],[4.128,0]],"v":[[7.475,0],[-0.001,7.5],[-7.475,0],[-0.001,-7.5]],"c":true}},"nm":"Path 1","mn":"ADBE Vector Shape - Group"},{"ty":"fl","c":{"a":0,"k":[1,0.267,0.357,1]},"o":{"a":0,"k":100},"r":1,"nm":"Fill 1","mn":"ADBE Vector Graphic - Fill"},{"ty":"tr","p":{"a":0,"k":[90.004,225.317],"ix":2},"a":{"a":0,"k":[0,0],"ix":1},"s":{"a":0,"k":[159,159],"ix":3},"r":{"a":0,"k":0,"ix":6},"o":{"a":0,"k":100,"ix":7},"sk":{"a":0,"k":0,"ix":4},"sa":{"a":0,"k":0,"ix":5},"nm":"Transform"}],"nm":"Group 180","np":2,"cix":2,"ix":56,"mn":"ADBE Vector Group"},{"ty":"gr","it":[{"ind":0,"ty":"sh","ix":1,"ks":{"a":0,"k":{"i":[[0,-1.621],[1.621,0],[0,1.621],[-1.62,0]],"o":[[0,1.621],[-1.62,0],[0,-1.621],[1.621,0]],"v":[[2.935,0],[-0.001,2.935],[-2.935,0],[-0.001,-2.935]],"c":true}},"nm":"Path 1","mn":"ADBE Vector Shape - Group"},{"ty":"fl","c":{"a":0,"k":[1,1,1,1]},"o":{"a":0,"k":100},"r":1,"nm":"Fill 1","mn":"ADBE Vector Graphic - Fill"},{"ty":"tr","p":{"a":0,"k":[180.219,144.956],"ix":2},"a":{"a":0,"k":[0,0],"ix":1},"s":{"a":0,"k":[207,207],"ix":3},"r":{"a":0,"k":0,"ix":6},"o":{"a":0,"k":100,"ix":7},"sk":{"a":0,"k":0,"ix":4},"sa":{"a":0,"k":0,"ix":5},"nm":"Transform"}],"nm":"Group 193","np":2,"cix":2,"ix":57,"mn":"ADBE Vector Group"},{"ty":"gr","it":[{"ind":0,"ty":"sh","ix":1,"ks":{"a":0,"k":{"i":[[0,-4.142],[4.128,0],[0,4.142],[-4.128,0]],"o":[[0,4.142],[-4.128,0],[0,-4.142],[4.128,0]],"v":[[7.475,0],[0,7.5],[-7.475,0],[0,-7.5]],"c":true}},"nm":"Path 1","mn":"ADBE Vector Shape - Group"},{"ty":"fl","c":{"a":0,"k":[1,0.267,0.357,1]},"o":{"a":0,"k":100},"r":1,"nm":"Fill 1","mn":"ADBE Vector Graphic - Fill"},{"ty":"tr","p":{"a":0,"k":[180.219,144.956],"ix":2},"a":{"a":0,"k":[0,0],"ix":1},"s":{"a":0,"k":[159,159],"ix":3},"r":{"a":0,"k":0,"ix":6},"o":{"a":0,"k":100,"ix":7},"sk":{"a":0,"k":0,"ix":4},"sa":{"a":0,"k":0,"ix":5},"nm":"Transform"}],"nm":"Group 194","np":2,"cix":2,"ix":58,"mn":"ADBE Vector Group"},{"ty":"gr","it":[{"ind":0,"ty":"sh","ix":1,"ks":{"a":0,"k":{"i":[[0,-1.621],[1.622,0],[0,1.621],[-1.62,0]],"o":[[0,1.621],[-1.62,0],[0,-1.621],[1.622,0]],"v":[[2.935,0],[-0.001,2.935],[-2.935,0],[-0.001,-2.935]],"c":true}},"nm":"Path 1","mn":"ADBE Vector Shape - Group"},{"ty":"fl","c":{"a":0,"k":[1,1,1,1]},"o":{"a":0,"k":100},"r":1,"nm":"Fill 1","mn":"ADBE Vector Graphic - Fill"},{"ty":"tr","p":{"a":0,"k":[178.591,198.563],"ix":2},"a":{"a":0,"k":[0,0],"ix":1},"s":{"a":0,"k":[207,207],"ix":3},"r":{"a":0,"k":0,"ix":6},"o":{"a":0,"k":100,"ix":7},"sk":{"a":0,"k":0,"ix":4},"sa":{"a":0,"k":0,"ix":5},"nm":"Transform"}],"nm":"Group 197","np":2,"cix":2,"ix":59,"mn":"ADBE Vector Group"},{"ty":"gr","it":[{"ind":0,"ty":"sh","ix":1,"ks":{"a":0,"k":{"i":[[0,-4.142],[4.128,0],[0,4.142],[-4.128,0]],"o":[[0,4.142],[-4.128,0],[0,-4.142],[4.128,0]],"v":[[7.475,0],[-0.001,7.5],[-7.475,0],[-0.001,-7.5]],"c":true}},"nm":"Path 1","mn":"ADBE Vector Shape - Group"},{"ty":"fl","c":{"a":0,"k":[1,0.267,0.357,1]},"o":{"a":0,"k":100},"r":1,"nm":"Fill 1","mn":"ADBE Vector Graphic - Fill"},{"ty":"tr","p":{"a":0,"k":[178.591,198.562],"ix":2},"a":{"a":0,"k":[0,0],"ix":1},"s":{"a":0,"k":[159,159],"ix":3},"r":{"a":0,"k":0,"ix":6},"o":{"a":0,"k":100,"ix":7},"sk":{"a":0,"k":0,"ix":4},"sa":{"a":0,"k":0,"ix":5},"nm":"Transform"}],"nm":"Group 198","np":2,"cix":2,"ix":60,"mn":"ADBE Vector Group"},{"ty":"gr","it":[{"ind":0,"ty":"sh","ix":1,"ks":{"a":0,"k":{"i":[[0,-1.621],[1.621,0],[0,1.621],[-1.62,0]],"o":[[0,1.621],[-1.62,0],[0,-1.621],[1.621,0]],"v":[[2.935,0],[-0.001,2.935],[-2.935,0],[-0.001,-2.935]],"c":true}},"nm":"Path 1","mn":"ADBE Vector Shape - Group"},{"ty":"fl","c":{"a":0,"k":[1,1,1,1]},"o":{"a":0,"k":100},"r":1,"nm":"Fill 1","mn":"ADBE Vector Graphic - Fill"},{"ty":"tr","p":{"a":0,"k":[143.978,198.563],"ix":2},"a":{"a":0,"k":[0,0],"ix":1},"s":{"a":0,"k":[207,207],"ix":3},"r":{"a":0,"k":0,"ix":6},"o":{"a":0,"k":100,"ix":7},"sk":{"a":0,"k":0,"ix":4},"sa":{"a":0,"k":0,"ix":5},"nm":"Transform"}],"nm":"Group 209","np":2,"cix":2,"ix":61,"mn":"ADBE Vector Group"},{"ty":"gr","it":[{"ind":0,"ty":"sh","ix":1,"ks":{"a":0,"k":{"i":[[0,-4.142],[4.128,0],[0,4.142],[-4.128,0]],"o":[[0,4.142],[-4.128,0],[0,-4.142],[4.128,0]],"v":[[7.475,0],[0,7.5],[-7.475,0],[0,-7.5]],"c":true}},"nm":"Path 1","mn":"ADBE Vector Shape - Group"},{"ty":"fl","c":{"a":0,"k":[1,0.267,0.357,1]},"o":{"a":0,"k":100},"r":1,"nm":"Fill 1","mn":"ADBE Vector Graphic - Fill"},{"ty":"tr","p":{"a":0,"k":[143.978,198.562],"ix":2},"a":{"a":0,"k":[0,0],"ix":1},"s":{"a":0,"k":[159,159],"ix":3},"r":{"a":0,"k":0,"ix":6},"o":{"a":0,"k":100,"ix":7},"sk":{"a":0,"k":0,"ix":4},"sa":{"a":0,"k":0,"ix":5},"nm":"Transform"}],"nm":"Group 210","np":2,"cix":2,"ix":62,"mn":"ADBE Vector Group"},{"ty":"gr","it":[{"ind":0,"ty":"sh","ix":1,"ks":{"a":0,"k":{"i":[[0,-1.621],[1.621,0],[0,1.621],[-1.62,0]],"o":[[0,1.621],[-1.62,0],[0,-1.621],[1.621,0]],"v":[[2.935,0],[-0.001,2.935],[-2.935,0],[-0.001,-2.935]],"c":true}},"nm":"Path 1","mn":"ADBE Vector Shape - Group"},{"ty":"fl","c":{"a":0,"k":[1,1,1,1]},"o":{"a":0,"k":100},"r":1,"nm":"Fill 1","mn":"ADBE Vector Graphic - Fill"},{"ty":"tr","p":{"a":0,"k":[107.978,198.563],"ix":2},"a":{"a":0,"k":[0,0],"ix":1},"s":{"a":0,"k":[207,207],"ix":3},"r":{"a":0,"k":0,"ix":6},"o":{"a":0,"k":100,"ix":7},"sk":{"a":0,"k":0,"ix":4},"sa":{"a":0,"k":0,"ix":5},"nm":"Transform"}],"nm":"Group 213","np":2,"cix":2,"ix":63,"mn":"ADBE Vector Group"},{"ty":"gr","it":[{"ind":0,"ty":"sh","ix":1,"ks":{"a":0,"k":{"i":[[0,-4.142],[4.128,0],[0,4.142],[-4.128,0]],"o":[[0,4.142],[-4.128,0],[0,-4.142],[4.128,0]],"v":[[7.475,0],[0,7.5],[-7.475,0],[0,-7.5]],"c":true}},"nm":"Path 1","mn":"ADBE Vector Shape - Group"},{"ty":"fl","c":{"a":0,"k":[1,0.267,0.357,1]},"o":{"a":0,"k":100},"r":1,"nm":"Fill 1","mn":"ADBE Vector Graphic - Fill"},{"ty":"tr","p":{"a":0,"k":[107.978,198.562],"ix":2},"a":{"a":0,"k":[0,0],"ix":1},"s":{"a":0,"k":[159,159],"ix":3},"r":{"a":0,"k":0,"ix":6},"o":{"a":0,"k":100,"ix":7},"sk":{"a":0,"k":0,"ix":4},"sa":{"a":0,"k":0,"ix":5},"nm":"Transform"}],"nm":"Group 214","np":2,"cix":2,"ix":64,"mn":"ADBE Vector Group"},{"ty":"gr","it":[{"ind":0,"ty":"sh","ix":1,"ks":{"a":0,"k":{"i":[[0,-1.621],[1.622,0],[0,1.621],[-1.62,0]],"o":[[0,1.621],[-1.62,0],[0,-1.621],[1.622,0]],"v":[[2.935,0],[-0.001,2.935],[-2.935,0],[-0.001,-2.935]],"c":true}},"nm":"Path 1","mn":"ADBE Vector Shape - Group"},{"ty":"fl","c":{"a":0,"k":[1,1,1,1]},"o":{"a":0,"k":100},"r":1,"nm":"Fill 1","mn":"ADBE Vector Graphic - Fill"},{"ty":"tr","p":{"a":0,"k":[161.936,172.08],"ix":2},"a":{"a":0,"k":[0,0],"ix":1},"s":{"a":0,"k":[207,207],"ix":3},"r":{"a":0,"k":0,"ix":6},"o":{"a":0,"k":100,"ix":7},"sk":{"a":0,"k":0,"ix":4},"sa":{"a":0,"k":0,"ix":5},"nm":"Transform"}],"nm":"Group 221","np":2,"cix":2,"ix":65,"mn":"ADBE Vector Group"},{"ty":"gr","it":[{"ind":0,"ty":"sh","ix":1,"ks":{"a":0,"k":{"i":[[0,-4.142],[4.128,0],[0,4.142],[-4.128,0]],"o":[[0,4.142],[-4.128,0],[0,-4.142],[4.128,0]],"v":[[7.475,0],[-0.001,7.5],[-7.475,0],[-0.001,-7.5]],"c":true}},"nm":"Path 1","mn":"ADBE Vector Shape - Group"},{"ty":"fl","c":{"a":0,"k":[1,0.267,0.357,1]},"o":{"a":0,"k":100},"r":1,"nm":"Fill 1","mn":"ADBE Vector Graphic - Fill"},{"ty":"tr","p":{"a":0,"k":[161.936,172.08],"ix":2},"a":{"a":0,"k":[0,0],"ix":1},"s":{"a":0,"k":[159,159],"ix":3},"r":{"a":0,"k":0,"ix":6},"o":{"a":0,"k":100,"ix":7},"sk":{"a":0,"k":0,"ix":4},"sa":{"a":0,"k":0,"ix":5},"nm":"Transform"}],"nm":"Group 222","np":2,"cix":2,"ix":66,"mn":"ADBE Vector Group"},{"ty":"gr","it":[{"ind":0,"ty":"sh","ix":1,"ks":{"a":0,"k":{"i":[[0,-1.621],[1.622,0],[0,1.621],[-1.62,0]],"o":[[0,1.621],[-1.62,0],[0,-1.621],[1.622,0]],"v":[[2.935,0],[-0.001,2.935],[-2.935,0],[-0.001,-2.935]],"c":true}},"nm":"Path 1","mn":"ADBE Vector Shape - Group"},{"ty":"fl","c":{"a":0,"k":[1,1,1,1]},"o":{"a":0,"k":100},"r":1,"nm":"Fill 1","mn":"ADBE Vector Graphic - Fill"},{"ty":"tr","p":{"a":0,"k":[125.936,172.08],"ix":2},"a":{"a":0,"k":[0,0],"ix":1},"s":{"a":0,"k":[207,207],"ix":3},"r":{"a":0,"k":0,"ix":6},"o":{"a":0,"k":100,"ix":7},"sk":{"a":0,"k":0,"ix":4},"sa":{"a":0,"k":0,"ix":5},"nm":"Transform"}],"nm":"Group 225","np":2,"cix":2,"ix":67,"mn":"ADBE Vector Group"},{"ty":"gr","it":[{"ind":0,"ty":"sh","ix":1,"ks":{"a":0,"k":{"i":[[0,-4.142],[4.128,0],[0,4.142],[-4.128,0]],"o":[[0,4.142],[-4.128,0],[0,-4.142],[4.128,0]],"v":[[7.475,0],[-0.001,7.5],[-7.475,0],[-0.001,-7.5]],"c":true}},"nm":"Path 1","mn":"ADBE Vector Shape - Group"},{"ty":"fl","c":{"a":0,"k":[1,0.267,0.357,1]},"o":{"a":0,"k":100},"r":1,"nm":"Fill 1","mn":"ADBE Vector Graphic - Fill"},{"ty":"tr","p":{"a":0,"k":[125.936,172.08],"ix":2},"a":{"a":0,"k":[0,0],"ix":1},"s":{"a":0,"k":[159,159],"ix":3},"r":{"a":0,"k":0,"ix":6},"o":{"a":0,"k":100,"ix":7},"sk":{"a":0,"k":0,"ix":4},"sa":{"a":0,"k":0,"ix":5},"nm":"Transform"}],"nm":"Group 226","np":2,"cix":2,"ix":68,"mn":"ADBE Vector Group"},{"ty":"gr","it":[{"ind":0,"ty":"sh","ix":1,"ks":{"a":0,"k":{"i":[[0,-1.621],[1.621,0],[0,1.621],[-1.62,0]],"o":[[0,1.621],[-1.62,0],[0,-1.621],[1.621,0]],"v":[[2.935,0],[-0.001,2.935],[-2.935,0],[-0.001,-2.935]],"c":true}},"nm":"Path 1","mn":"ADBE Vector Shape - Group"},{"ty":"fl","c":{"a":0,"k":[1,1,1,1]},"o":{"a":0,"k":100},"r":1,"nm":"Fill 1","mn":"ADBE Vector Graphic - Fill"},{"ty":"tr","p":{"a":0,"k":[144.988,144.956],"ix":2},"a":{"a":0,"k":[0,0],"ix":1},"s":{"a":0,"k":[207,207],"ix":3},"r":{"a":0,"k":0,"ix":6},"o":{"a":0,"k":100,"ix":7},"sk":{"a":0,"k":0,"ix":4},"sa":{"a":0,"k":0,"ix":5},"nm":"Transform"}],"nm":"Group 229","np":2,"cix":2,"ix":69,"mn":"ADBE Vector Group"},{"ty":"gr","it":[{"ind":0,"ty":"sh","ix":1,"ks":{"a":0,"k":{"i":[[0,-4.142],[4.128,0],[0,4.142],[-4.128,0]],"o":[[0,4.142],[-4.128,0],[0,-4.142],[4.128,0]],"v":[[7.475,0],[0,7.5],[-7.475,0],[0,-7.5]],"c":true}},"nm":"Path 1","mn":"ADBE Vector Shape - Group"},{"ty":"fl","c":{"a":0,"k":[1,0.267,0.357,1]},"o":{"a":0,"k":100},"r":1,"nm":"Fill 1","mn":"ADBE Vector Graphic - Fill"},{"ty":"tr","p":{"a":0,"k":[144.987,144.956],"ix":2},"a":{"a":0,"k":[0,0],"ix":1},"s":{"a":0,"k":[159,159],"ix":3},"r":{"a":0,"k":0,"ix":6},"o":{"a":0,"k":100,"ix":7},"sk":{"a":0,"k":0,"ix":4},"sa":{"a":0,"k":0,"ix":5},"nm":"Transform"}],"nm":"Group 230","np":2,"cix":2,"ix":70,"mn":"ADBE Vector Group"},{"ty":"gr","it":[{"ind":0,"ty":"sh","ix":1,"ks":{"a":0,"k":{"i":[[0,-1.621],[1.621,0],[0,1.621],[-1.62,0]],"o":[[0,1.621],[-1.62,0],[0,-1.621],[1.621,0]],"v":[[2.935,0],[-0.001,2.935],[-2.935,0],[-0.001,-2.935]],"c":true}},"nm":"Path 1","mn":"ADBE Vector Shape - Group"},{"ty":"fl","c":{"a":0,"k":[1,1,1,1]},"o":{"a":0,"k":100},"r":1,"nm":"Fill 1","mn":"ADBE Vector Graphic - Fill"},{"ty":"tr","p":{"a":0,"k":[106.988,144.956],"ix":2},"a":{"a":0,"k":[0,0],"ix":1},"s":{"a":0,"k":[207,207],"ix":3},"r":{"a":0,"k":0,"ix":6},"o":{"a":0,"k":100,"ix":7},"sk":{"a":0,"k":0,"ix":4},"sa":{"a":0,"k":0,"ix":5},"nm":"Transform"}],"nm":"Group 233","np":2,"cix":2,"ix":71,"mn":"ADBE Vector Group"},{"ty":"gr","it":[{"ind":0,"ty":"sh","ix":1,"ks":{"a":0,"k":{"i":[[0,-4.142],[4.128,0],[0,4.142],[-4.128,0]],"o":[[0,4.142],[-4.128,0],[0,-4.142],[4.128,0]],"v":[[7.475,0],[0,7.5],[-7.475,0],[0,-7.5]],"c":true}},"nm":"Path 1","mn":"ADBE Vector Shape - Group"},{"ty":"fl","c":{"a":0,"k":[1,0.267,0.357,1]},"o":{"a":0,"k":100},"r":1,"nm":"Fill 1","mn":"ADBE Vector Graphic - Fill"},{"ty":"tr","p":{"a":0,"k":[106.987,144.956],"ix":2},"a":{"a":0,"k":[0,0],"ix":1},"s":{"a":0,"k":[159,159],"ix":3},"r":{"a":0,"k":0,"ix":6},"o":{"a":0,"k":100,"ix":7},"sk":{"a":0,"k":0,"ix":4},"sa":{"a":0,"k":0,"ix":5},"nm":"Transform"}],"nm":"Group 234","np":2,"cix":2,"ix":72,"mn":"ADBE Vector Group"},{"ty":"gr","it":[{"ind":0,"ty":"sh","ix":1,"ks":{"a":0,"k":{"i":[[0,-1.621],[1.621,0],[0,1.621],[-1.62,0]],"o":[[0,1.621],[-1.62,0],[0,-1.621],[1.621,0]],"v":[[2.935,0],[-0.001,2.935],[-2.935,0],[-0.001,-2.935]],"c":true}},"nm":"Path 1","mn":"ADBE Vector Shape - Group"},{"ty":"fl","c":{"a":0,"k":[1,1,1,1]},"o":{"a":0,"k":100},"r":1,"nm":"Fill 1","mn":"ADBE Vector Graphic - Fill"},{"ty":"tr","p":{"a":0,"k":[123.177,118.445],"ix":2},"a":{"a":0,"k":[0,0],"ix":1},"s":{"a":0,"k":[207,207],"ix":3},"r":{"a":0,"k":0,"ix":6},"o":{"a":0,"k":100,"ix":7},"sk":{"a":0,"k":0,"ix":4},"sa":{"a":0,"k":0,"ix":5},"nm":"Transform"}],"nm":"Group 241","np":2,"cix":2,"ix":73,"mn":"ADBE Vector Group"},{"ty":"gr","it":[{"ind":0,"ty":"sh","ix":1,"ks":{"a":0,"k":{"i":[[0,-4.142],[4.128,0],[0,4.142],[-4.128,0]],"o":[[0,4.142],[-4.128,0],[0,-4.142],[4.128,0]],"v":[[7.475,0],[-0.001,7.5],[-7.475,0],[-0.001,-7.5]],"c":true}},"nm":"Path 1","mn":"ADBE Vector Shape - Group"},{"ty":"fl","c":{"a":0,"k":[1,0.267,0.357,1]},"o":{"a":0,"k":100},"r":1,"nm":"Fill 1","mn":"ADBE Vector Graphic - Fill"},{"ty":"tr","p":{"a":0,"k":[123.177,118.445],"ix":2},"a":{"a":0,"k":[0,0],"ix":1},"s":{"a":0,"k":[159,159],"ix":3},"r":{"a":0,"k":0,"ix":6},"o":{"a":0,"k":100,"ix":7},"sk":{"a":0,"k":0,"ix":4},"sa":{"a":0,"k":0,"ix":5},"nm":"Transform"}],"nm":"Group 242","np":2,"cix":2,"ix":74,"mn":"ADBE Vector Group"},{"ty":"gr","it":[{"ind":0,"ty":"sh","ix":1,"ks":{"a":0,"k":{"i":[[0,-1.621],[1.621,0],[0,1.621],[-1.62,0]],"o":[[0,1.621],[-1.62,0],[0,-1.621],[1.621,0]],"v":[[2.935,0],[-0.001,2.935],[-2.935,0],[-0.001,-2.935]],"c":true}},"nm":"Path 1","mn":"ADBE Vector Shape - Group"},{"ty":"fl","c":{"a":0,"k":[1,1,1,1]},"o":{"a":0,"k":100},"r":1,"nm":"Fill 1","mn":"ADBE Vector Graphic - Fill"},{"ty":"tr","p":{"a":0,"k":[87.177,118.445],"ix":2},"a":{"a":0,"k":[0,0],"ix":1},"s":{"a":0,"k":[207,207],"ix":3},"r":{"a":0,"k":0,"ix":6},"o":{"a":0,"k":100,"ix":7},"sk":{"a":0,"k":0,"ix":4},"sa":{"a":0,"k":0,"ix":5},"nm":"Transform"}],"nm":"Group 245","np":2,"cix":2,"ix":75,"mn":"ADBE Vector Group"},{"ty":"gr","it":[{"ind":0,"ty":"sh","ix":1,"ks":{"a":0,"k":{"i":[[0,-4.142],[4.128,0],[0,4.142],[-4.128,0]],"o":[[0,4.142],[-4.128,0],[0,-4.142],[4.128,0]],"v":[[7.475,0],[-0.001,7.5],[-7.475,0],[-0.001,-7.5]],"c":true}},"nm":"Path 1","mn":"ADBE Vector Shape - Group"},{"ty":"fl","c":{"a":0,"k":[1,0.267,0.357,1]},"o":{"a":0,"k":100},"r":1,"nm":"Fill 1","mn":"ADBE Vector Graphic - Fill"},{"ty":"tr","p":{"a":0,"k":[87.177,118.445],"ix":2},"a":{"a":0,"k":[0,0],"ix":1},"s":{"a":0,"k":[159,159],"ix":3},"r":{"a":0,"k":0,"ix":6},"o":{"a":0,"k":100,"ix":7},"sk":{"a":0,"k":0,"ix":4},"sa":{"a":0,"k":0,"ix":5},"nm":"Transform"}],"nm":"Group 246","np":2,"cix":2,"ix":76,"mn":"ADBE Vector Group"},{"ty":"gr","it":[{"ind":0,"ty":"sh","ix":1,"ks":{"a":0,"k":{"i":[[0,-1.621],[1.621,0],[0,1.621],[-1.62,0]],"o":[[0,1.621],[-1.62,0],[0,-1.621],[1.621,0]],"v":[[2.935,-0.001],[-0.001,2.935],[-2.935,-0.001],[-0.001,-2.935]],"c":true}},"nm":"Path 1","mn":"ADBE Vector Shape - Group"},{"ty":"fl","c":{"a":0,"k":[1,1,1,1]},"o":{"a":0,"k":100},"r":1,"nm":"Fill 1","mn":"ADBE Vector Graphic - Fill"},{"ty":"tr","p":{"a":0,"k":[105.203,89.996],"ix":2},"a":{"a":0,"k":[0,0],"ix":1},"s":{"a":0,"k":[207,207],"ix":3},"r":{"a":0,"k":0,"ix":6},"o":{"a":0,"k":100,"ix":7},"sk":{"a":0,"k":0,"ix":4},"sa":{"a":0,"k":0,"ix":5},"nm":"Transform"}],"nm":"Group 259","np":2,"cix":2,"ix":77,"mn":"ADBE Vector Group"},{"ty":"gr","it":[{"ind":0,"ty":"sh","ix":1,"ks":{"a":0,"k":{"i":[[0,-4.142],[4.128,0],[0,4.142],[-4.128,0]],"o":[[0,4.142],[-4.128,0],[0,-4.142],[4.128,0]],"v":[[7.475,0],[0,7.5],[-7.475,0],[0,-7.5]],"c":true}},"nm":"Path 1","mn":"ADBE Vector Shape - Group"},{"ty":"fl","c":{"a":0,"k":[1,0.267,0.357,1]},"o":{"a":0,"k":100},"r":1,"nm":"Fill 1","mn":"ADBE Vector Graphic - Fill"},{"ty":"tr","p":{"a":0,"k":[105.202,89.995],"ix":2},"a":{"a":0,"k":[0,0],"ix":1},"s":{"a":0,"k":[159,159],"ix":3},"r":{"a":0,"k":0,"ix":6},"o":{"a":0,"k":100,"ix":7},"sk":{"a":0,"k":0,"ix":4},"sa":{"a":0,"k":0,"ix":5},"nm":"Transform"}],"nm":"Group 260","np":2,"cix":2,"ix":78,"mn":"ADBE Vector Group"},{"ty":"gr","it":[{"ind":0,"ty":"sh","ix":1,"ks":{"a":0,"k":{"i":[[0,-1.621],[1.621,0],[0,1.621],[-1.62,0]],"o":[[0,1.621],[-1.62,0],[0,-1.621],[1.621,0]],"v":[[2.935,-0.001],[-0.001,2.935],[-2.935,-0.001],[-0.001,-2.935]],"c":true}},"nm":"Path 1","mn":"ADBE Vector Shape - Group"},{"ty":"fl","c":{"a":0,"k":[1,1,1,1]},"o":{"a":0,"k":100},"r":1,"nm":"Fill 1","mn":"ADBE Vector Graphic - Fill"},{"ty":"tr","p":{"a":0,"k":[69.203,89.996],"ix":2},"a":{"a":0,"k":[0,0],"ix":1},"s":{"a":0,"k":[207,207],"ix":3},"r":{"a":0,"k":0,"ix":6},"o":{"a":0,"k":100,"ix":7},"sk":{"a":0,"k":0,"ix":4},"sa":{"a":0,"k":0,"ix":5},"nm":"Transform"}],"nm":"Group 263","np":2,"cix":2,"ix":79,"mn":"ADBE Vector Group"},{"ty":"gr","it":[{"ind":0,"ty":"sh","ix":1,"ks":{"a":0,"k":{"i":[[0,-4.142],[4.128,0],[0,4.142],[-4.128,0]],"o":[[0,4.142],[-4.128,0],[0,-4.142],[4.128,0]],"v":[[7.475,0],[0,7.5],[-7.475,0],[0,-7.5]],"c":true}},"nm":"Path 1","mn":"ADBE Vector Shape - Group"},{"ty":"fl","c":{"a":0,"k":[1,0.267,0.357,1]},"o":{"a":0,"k":100},"r":1,"nm":"Fill 1","mn":"ADBE Vector Graphic - Fill"},{"ty":"tr","p":{"a":0,"k":[69.202,89.995],"ix":2},"a":{"a":0,"k":[0,0],"ix":1},"s":{"a":0,"k":[159,159],"ix":3},"r":{"a":0,"k":0,"ix":6},"o":{"a":0,"k":100,"ix":7},"sk":{"a":0,"k":0,"ix":4},"sa":{"a":0,"k":0,"ix":5},"nm":"Transform"}],"nm":"Group 264","np":2,"cix":2,"ix":80,"mn":"ADBE Vector Group"},{"ty":"gr","it":[{"ind":0,"ty":"sh","ix":1,"ks":{"a":0,"k":{"i":[[0,-1.621],[1.621,0],[0,1.621],[-1.62,0]],"o":[[0,1.621],[-1.62,0],[0,-1.621],[1.621,0]],"v":[[2.935,0],[-0.001,2.935],[-2.935,0],[-0.001,-2.935]],"c":true}},"nm":"Path 1","mn":"ADBE Vector Shape - Group"},{"ty":"fl","c":{"a":0,"k":[1,1,1,1]},"o":{"a":0,"k":100},"r":1,"nm":"Fill 1","mn":"ADBE Vector Graphic - Fill"},{"ty":"tr","p":{"a":0,"k":[86.675,61.523],"ix":2},"a":{"a":0,"k":[0,0],"ix":1},"s":{"a":0,"k":[207,207],"ix":3},"r":{"a":0,"k":0,"ix":6},"o":{"a":0,"k":100,"ix":7},"sk":{"a":0,"k":0,"ix":4},"sa":{"a":0,"k":0,"ix":5},"nm":"Transform"}],"nm":"Group 265","np":2,"cix":2,"ix":81,"mn":"ADBE Vector Group"},{"ty":"gr","it":[{"ind":0,"ty":"sh","ix":1,"ks":{"a":0,"k":{"i":[[0,-4.142],[4.128,0],[0,4.142],[-4.128,0]],"o":[[0,4.142],[-4.128,0],[0,-4.142],[4.128,0]],"v":[[7.475,0],[-0.001,7.5],[-7.475,0],[-0.001,-7.5]],"c":true}},"nm":"Path 1","mn":"ADBE Vector Shape - Group"},{"ty":"fl","c":{"a":0,"k":[1,0.267,0.357,1]},"o":{"a":0,"k":100},"r":1,"nm":"Fill 1","mn":"ADBE Vector Graphic - Fill"},{"ty":"tr","p":{"a":0,"k":[86.675,61.523],"ix":2},"a":{"a":0,"k":[0,0],"ix":1},"s":{"a":0,"k":[159,159],"ix":3},"r":{"a":0,"k":0,"ix":6},"o":{"a":0,"k":100,"ix":7},"sk":{"a":0,"k":0,"ix":4},"sa":{"a":0,"k":0,"ix":5},"nm":"Transform"}],"nm":"Group 266","np":2,"cix":2,"ix":82,"mn":"ADBE Vector Group"},{"ty":"gr","it":[{"ind":0,"ty":"sh","ix":1,"ks":{"a":0,"k":{"i":[[0,-1.621],[1.621,0],[0,1.621],[-1.62,0]],"o":[[0,1.621],[-1.62,0],[0,-1.621],[1.621,0]],"v":[[2.935,0],[-0.001,2.935],[-2.935,0],[-0.001,-2.935]],"c":true}},"nm":"Path 1","mn":"ADBE Vector Shape - Group"},{"ty":"fl","c":{"a":0,"k":[1,1,1,1]},"o":{"a":0,"k":100},"r":1,"nm":"Fill 1","mn":"ADBE Vector Graphic - Fill"},{"ty":"tr","p":{"a":0,"k":[50.675,61.523],"ix":2},"a":{"a":0,"k":[0,0],"ix":1},"s":{"a":0,"k":[207,207],"ix":3},"r":{"a":0,"k":0,"ix":6},"o":{"a":0,"k":100,"ix":7},"sk":{"a":0,"k":0,"ix":4},"sa":{"a":0,"k":0,"ix":5},"nm":"Transform"}],"nm":"Group 269","np":2,"cix":2,"ix":83,"mn":"ADBE Vector Group"},{"ty":"gr","it":[{"ind":0,"ty":"sh","ix":1,"ks":{"a":0,"k":{"i":[[0,-4.142],[4.128,0],[0,4.142],[-4.128,0]],"o":[[0,4.142],[-4.128,0],[0,-4.142],[4.128,0]],"v":[[7.475,0],[-0.001,7.5],[-7.475,0],[-0.001,-7.5]],"c":true}},"nm":"Path 1","mn":"ADBE Vector Shape - Group"},{"ty":"fl","c":{"a":0,"k":[1,0.267,0.357,1]},"o":{"a":0,"k":100},"r":1,"nm":"Fill 1","mn":"ADBE Vector Graphic - Fill"},{"ty":"tr","p":{"a":0,"k":[50.675,61.523],"ix":2},"a":{"a":0,"k":[0,0],"ix":1},"s":{"a":0,"k":[159,159],"ix":3},"r":{"a":0,"k":0,"ix":6},"o":{"a":0,"k":100,"ix":7},"sk":{"a":0,"k":0,"ix":4},"sa":{"a":0,"k":0,"ix":5},"nm":"Transform"}],"nm":"Group 270","np":2,"cix":2,"ix":84,"mn":"ADBE Vector Group"},{"ty":"gr","it":[{"ind":0,"ty":"sh","ix":1,"ks":{"a":0,"k":{"i":[[0,-1.621],[1.621,0],[0,1.621],[-1.62,0]],"o":[[0,1.621],[-1.62,0],[0,-1.621],[1.621,0]],"v":[[2.935,0],[-0.001,2.935],[-2.935,0],[-0.001,-2.935]],"c":true}},"nm":"Path 1","mn":"ADBE Vector Shape - Group"},{"ty":"fl","c":{"a":0,"k":[1,1,1,1]},"o":{"a":0,"k":100},"r":1,"nm":"Fill 1","mn":"ADBE Vector Graphic - Fill"},{"ty":"tr","p":{"a":0,"k":[67.527,34.613],"ix":2},"a":{"a":0,"k":[0,0],"ix":1},"s":{"a":0,"k":[207,207],"ix":3},"r":{"a":0,"k":0,"ix":6},"o":{"a":0,"k":100,"ix":7},"sk":{"a":0,"k":0,"ix":4},"sa":{"a":0,"k":0,"ix":5},"nm":"Transform"}],"nm":"Group 271","np":2,"cix":2,"ix":85,"mn":"ADBE Vector Group"},{"ty":"gr","it":[{"ind":0,"ty":"sh","ix":1,"ks":{"a":0,"k":{"i":[[0,-4.142],[4.128,0],[0,4.142],[-4.128,0]],"o":[[0,4.142],[-4.128,0],[0,-4.142],[4.128,0]],"v":[[7.475,0],[0,7.5],[-7.475,0],[0,-7.5]],"c":true}},"nm":"Path 1","mn":"ADBE Vector Shape - Group"},{"ty":"fl","c":{"a":0,"k":[1,0.267,0.357,1]},"o":{"a":0,"k":100},"r":1,"nm":"Fill 1","mn":"ADBE Vector Graphic - Fill"},{"ty":"tr","p":{"a":0,"k":[67.527,34.613],"ix":2},"a":{"a":0,"k":[0,0],"ix":1},"s":{"a":0,"k":[159,159],"ix":3},"r":{"a":0,"k":0,"ix":6},"o":{"a":0,"k":100,"ix":7},"sk":{"a":0,"k":0,"ix":4},"sa":{"a":0,"k":0,"ix":5},"nm":"Transform"}],"nm":"Group 272","np":2,"cix":2,"ix":86,"mn":"ADBE Vector Group"},{"ty":"gr","it":[{"ind":0,"ty":"sh","ix":1,"ks":{"a":0,"k":{"i":[[0,-1.621],[1.621,0],[0,1.621],[-1.62,0]],"o":[[0,1.621],[-1.62,0],[0,-1.621],[1.621,0]],"v":[[2.935,0],[-0.001,2.935],[-2.935,0],[-0.001,-2.935]],"c":true}},"nm":"Path 1","mn":"ADBE Vector Shape - Group"},{"ty":"fl","c":{"a":0,"k":[1,1,1,1]},"o":{"a":0,"k":100},"r":1,"nm":"Fill 1","mn":"ADBE Vector Graphic - Fill"},{"ty":"tr","p":{"a":0,"k":[31.527,34.613],"ix":2},"a":{"a":0,"k":[0,0],"ix":1},"s":{"a":0,"k":[207,207],"ix":3},"r":{"a":0,"k":0,"ix":6},"o":{"a":0,"k":100,"ix":7},"sk":{"a":0,"k":0,"ix":4},"sa":{"a":0,"k":0,"ix":5},"nm":"Transform"}],"nm":"Group 275","np":2,"cix":2,"ix":87,"mn":"ADBE Vector Group"},{"ty":"gr","it":[{"ind":0,"ty":"sh","ix":1,"ks":{"a":0,"k":{"i":[[0,-4.142],[4.128,0],[0,4.142],[-4.128,0]],"o":[[0,4.142],[-4.128,0],[0,-4.142],[4.128,0]],"v":[[7.475,0],[0,7.5],[-7.475,0],[0,-7.5]],"c":true}},"nm":"Path 1","mn":"ADBE Vector Shape - Group"},{"ty":"fl","c":{"a":0,"k":[1,0.267,0.357,1]},"o":{"a":0,"k":100},"r":1,"nm":"Fill 1","mn":"ADBE Vector Graphic - Fill"},{"ty":"tr","p":{"a":0,"k":[31.527,34.613],"ix":2},"a":{"a":0,"k":[0,0],"ix":1},"s":{"a":0,"k":[159,159],"ix":3},"r":{"a":0,"k":0,"ix":6},"o":{"a":0,"k":100,"ix":7},"sk":{"a":0,"k":0,"ix":4},"sa":{"a":0,"k":0,"ix":5},"nm":"Transform"}],"nm":"Group 276","np":2,"cix":2,"ix":88,"mn":"ADBE Vector Group"}],"ip":0,"op":120,"st":0,"bm":0}]}],"layers":[{"ddd":0,"ind":1,"ty":0,"nm":"X_light","parent":5,"refId":"comp_0","sr":1,"ks":{"o":{"a":1,"k":[{"i":{"x":[0.88],"y":[0.994]},"o":{"x":[0.333],"y":[0]},"n":["0p88_0p994_0p333_0"],"t":4,"s":[0],"e":[0]},{"i":{"x":[0.544],"y":[0.995]},"o":{"x":[0.587],"y":[0.002]},"n":["0p544_0p995_0p587_0p002"],"t":6,"s":[0],"e":[99.731]},{"i":{"x":[0.594],"y":[0.999]},"o":{"x":[0.364],"y":[0.002]},"n":["0p594_0p999_0p364_0p002"],"t":12,"s":[99.731],"e":[0]},{"t":18}]},"r":{"a":0,"k":0},"p":{"a":0,"k":[256.993,338.445,0]},"a":{"a":0,"k":[326.5,580,0]},"s":{"a":0,"k":[100,100,100]}},"ao":0,"w":653,"h":1160,"ip":-21,"op":99,"st":-21,"bm":0},{"ddd":0,"ind":3,"ty":4,"nm":"X1","parent":5,"sr":1,"ks":{"o":{"a":0,"k":100},"r":{"a":0,"k":0},"p":{"a":0,"k":[254.287,306.07,0]},"a":{"a":0,"k":[287.513,349.294,0]},"s":{"a":0,"k":[100,100,100]}},"ao":0,"shapes":[{"ty":"gr","it":[{"ind":0,"ty":"sh","ix":1,"ks":{"a":0,"k":{"i":[[0,0],[0,0]],"o":[[0,0],[0,0]],"v":[[-125.013,186.794],[125.012,-186.794]],"c":false}},"nm":"Path 1","mn":"ADBE Vector Shape - Group"},{"ty":"st","c":{"a":0,"k":[0.765,0.118,0.165,1]},"o":{"a":0,"k":100},"w":{"a":0,"k":65},"lc":1,"lj":1,"ml":10,"nm":"Stroke 1","mn":"ADBE Vector Graphic - Stroke"},{"ty":"tr","p":{"a":0,"k":[287.513,349.294],"ix":2},"a":{"a":0,"k":[0,0],"ix":1},"s":{"a":0,"k":[100,100],"ix":3},"r":{"a":0,"k":0,"ix":6},"o":{"a":0,"k":100,"ix":7},"sk":{"a":0,"k":0,"ix":4},"sa":{"a":0,"k":0,"ix":5},"nm":"Transform"}],"nm":"Group 1","np":2,"cix":2,"ix":1,"mn":"ADBE Vector Group"}],"ip":-21,"op":99,"st":-21,"bm":0},{"ddd":0,"ind":4,"ty":4,"nm":"X2","parent":5,"sr":1,"ks":{"o":{"a":0,"k":100},"r":{"a":0,"k":0},"p":{"a":0,"k":[260.067,305.231,0]},"a":{"a":0,"k":[287.513,348.356,0]},"s":{"a":0,"k":[100,100,100]}},"ao":0,"shapes":[{"ty":"gr","it":[{"ind":0,"ty":"sh","ix":1,"ks":{"a":0,"k":{"i":[[0,0],[0,0]],"o":[[0,0],[0,0]],"v":[[125.013,185.856],[-125.012,-185.856]],"c":false}},"nm":"Path 1","mn":"ADBE Vector Shape - Group"},{"ty":"st","c":{"a":0,"k":[0.765,0.118,0.165,1]},"o":{"a":0,"k":100},"w":{"a":0,"k":65},"lc":1,"lj":1,"ml":10,"nm":"Stroke 1","mn":"ADBE Vector Graphic - Stroke"},{"ty":"tr","p":{"a":0,"k":[287.513,348.356],"ix":2},"a":{"a":0,"k":[0,0],"ix":1},"s":{"a":0,"k":[100,100],"ix":3},"r":{"a":0,"k":0,"ix":6},"o":{"a":0,"k":100,"ix":7},"sk":{"a":0,"k":0,"ix":4},"sa":{"a":0,"k":0,"ix":5},"nm":"Transform"}],"nm":"Group 1","np":2,"cix":2,"ix":1,"mn":"ADBE Vector Group"}],"ip":-21,"op":99,"st":-21,"bm":0},{"ddd":0,"ind":5,"ty":4,"nm":"box","sr":1,"ks":{"o":{"a":0,"k":100},"r":{"a":0,"k":0},"p":{"a":0,"k":[191.305,234.057,0]},"a":{"a":0,"k":[258.298,304.503,0]},"s":{"a":1,"k":[{"t":-4,"s":[100,100,100],"h":1},{"i":{"x":[0.667,0.667,0.667],"y":[1,1,1]},"o":{"x":[0.333,0.333,0.333],"y":[0,0,0]},"n":["0p667_1_0p333_0","0p667_1_0p333_0","0p667_1_0p333_0"],"t":4,"s":[100,100,100],"e":[96,96,100]},{"i":{"x":[0.667,0.667,0.667],"y":[1,1,1]},"o":{"x":[0.054,0.054,0.333],"y":[0.109,0.109,0]},"n":["0p667_1_0p054_0p109","0p667_1_0p054_0p109","0p667_1_0p333_0"],"t":6,"s":[96,96,100],"e":[94,94,100]},{"i":{"x":[0.667,0.667,0.667],"y":[1,1,1]},"o":{"x":[1,1,0.333],"y":[-0.023,-0.023,0]},"n":["0p667_1_1_-0p023","0p667_1_1_-0p023","0p667_1_0p333_0"],"t":8,"s":[94,94,100],"e":[106,106,100]},{"i":{"x":[0.667,0.667,0.667],"y":[1,1,1]},"o":{"x":[0.232,0.232,0.333],"y":[0.304,0.304,0]},"n":["0p667_1_0p232_0p304","0p667_1_0p232_0p304","0p667_1_0p333_0"],"t":10,"s":[106,106,100],"e":[108,108,100]},{"i":{"x":[0.667,0.667,0.667],"y":[1,1,1]},"o":{"x":[0.333,0.333,0.333],"y":[0,0,0]},"n":["0p667_1_0p333_0","0p667_1_0p333_0","0p667_1_0p333_0"],"t":12,"s":[108,108,100],"e":[106,106,100]},{"i":{"x":[0.667,0.667,0.667],"y":[1,1,1]},"o":{"x":[0.232,0.232,0.333],"y":[0,0,0]},"n":["0p667_1_0p232_0","0p667_1_0p232_0","0p667_1_0p333_0"],"t":14,"s":[106,106,100],"e":[97,97,100]},{"i":{"x":[0.667,0.667,0.667],"y":[1,1,1]},"o":{"x":[0.333,0.333,0.333],"y":[0,0,0]},"n":["0p667_1_0p333_0","0p667_1_0p333_0","0p667_1_0p333_0"],"t":16,"s":[97,97,100],"e":[101.5,101.5,100]},{"i":{"x":[0.833,0.833,0.833],"y":[1,1,1]},"o":{"x":[0.167,0.167,0.167],"y":[-0.002,-0.002,0]},"n":["0p833_1_0p167_-0p002","0p833_1_0p167_-0p002","0p833_1_0p167_0"],"t":20,"s":[101.5,101.5,100],"e":[100,100,100]},{"t":24,"s":[100,100,100],"h":1},{"t":26,"s":[100,100,100],"h":1}]}},"ao":0,"shapes":[{"ty":"gr","it":[{"ind":0,"ty":"sh","ix":1,"ks":{"a":0,"k":{"i":[[16.016,0],[0,0],[0,16.016],[0,0],[-16.016,0],[0,0],[0,-16.016],[0,0]],"o":[[0,0],[-16.016,0],[0,0],[0,-16.016],[0,0],[16.016,0],[0,0],[0,16.016]],"v":[[111.798,187.002],[-111.798,187.002],[-140.798,158.002],[-140.798,-158.002],[-111.798,-187.002],[111.798,-187.002],[140.798,-158.002],[140.798,158.002]],"c":true}},"nm":"Path 1","mn":"ADBE Vector Shape - Group"},{"ty":"st","c":{"a":0,"k":[0.765,0.118,0.165,1]},"o":{"a":0,"k":100},"w":{"a":0,"k":47},"lc":1,"lj":1,"ml":10,"nm":"Stroke 1","mn":"ADBE Vector Graphic - Stroke"},{"ty":"tr","p":{"a":0,"k":[258.298,304.503],"ix":2},"a":{"a":0,"k":[0,0],"ix":1},"s":{"a":0,"k":[100,100],"ix":3},"r":{"a":0,"k":0,"ix":6},"o":{"a":0,"k":100,"ix":7},"sk":{"a":0,"k":0,"ix":4},"sa":{"a":0,"k":0,"ix":5},"nm":"Transform"}],"nm":"Group 1","np":2,"cix":2,"ix":1,"mn":"ADBE Vector Group"}],"ip":-21,"op":99,"st":-21,"bm":0},{"ddd":0,"ind":6,"ty":4,"nm":"X1_shadow","parent":5,"sr":1,"ks":{"o":{"a":0,"k":100},"r":{"a":0,"k":0},"p":{"a":0,"k":[254.287,306.07,0]},"a":{"a":0,"k":[287.513,349.294,0]},"s":{"a":0,"k":[100,100,100]}},"ao":0,"shapes":[{"ty":"gr","it":[{"ind":0,"ty":"sh","ix":1,"ks":{"a":0,"k":{"i":[[0,0],[0,0]],"o":[[0,0],[0,0]],"v":[[-125.013,186.794],[125.012,-186.794]],"c":false}},"nm":"Path 1","mn":"ADBE Vector Shape - Group"},{"ty":"st","c":{"a":0,"k":[0.765,0.118,0.165,1]},"o":{"a":0,"k":100},"w":{"a":0,"k":65},"lc":1,"lj":1,"ml":10,"nm":"Stroke 1","mn":"ADBE Vector Graphic - Stroke"},{"ty":"tr","p":{"a":0,"k":[287.513,349.294],"ix":2},"a":{"a":0,"k":[0,0],"ix":1},"s":{"a":0,"k":[100,100],"ix":3},"r":{"a":0,"k":0,"ix":6},"o":{"a":0,"k":100,"ix":7},"sk":{"a":0,"k":0,"ix":4},"sa":{"a":0,"k":0,"ix":5},"nm":"Transform"}],"nm":"Group 1","np":2,"cix":2,"ix":1,"mn":"ADBE Vector Group"}],"ip":-21,"op":99,"st":-21,"bm":0},{"ddd":0,"ind":7,"ty":4,"nm":"X2_shadow","parent":5,"sr":1,"ks":{"o":{"a":0,"k":100},"r":{"a":0,"k":0},"p":{"a":0,"k":[250.975,312.449,0]},"a":{"a":0,"k":[287.513,348.357,0]},"s":{"a":0,"k":[100,100,100]}},"ao":0,"shapes":[{"ty":"gr","it":[{"ind":0,"ty":"sh","ix":1,"ks":{"a":0,"k":{"i":[[0,0],[0,0]],"o":[[0,0],[0,0]],"v":[[125.012,185.857],[-125.012,-185.856]],"c":false}},"nm":"Path 1","mn":"ADBE Vector Shape - Group"},{"ty":"st","c":{"a":0,"k":[0.616,0.039,0.082,1]},"o":{"a":0,"k":100},"w":{"a":0,"k":65},"lc":1,"lj":1,"ml":10,"nm":"Stroke 1","mn":"ADBE Vector Graphic - Stroke"},{"ty":"tr","p":{"a":0,"k":[287.512,348.357],"ix":2},"a":{"a":0,"k":[0,0],"ix":1},"s":{"a":0,"k":[100,100],"ix":3},"r":{"a":0,"k":0,"ix":6},"o":{"a":0,"k":100,"ix":7},"sk":{"a":0,"k":0,"ix":4},"sa":{"a":0,"k":0,"ix":5},"nm":"Transform"}],"nm":"Group 1","np":2,"cix":2,"ix":1,"mn":"ADBE Vector Group"}],"ip":-21,"op":99,"st":-21,"bm":0},{"ddd":0,"ind":8,"ty":4,"nm":"box_shadow","parent":5,"sr":1,"ks":{"o":{"a":0,"k":100},"r":{"a":0,"k":0},"p":{"a":0,"k":[258.298,312.498,0]},"a":{"a":0,"k":[258.298,304.503,0]},"s":{"a":0,"k":[100,100,100]}},"ao":0,"shapes":[{"ty":"gr","it":[{"ind":0,"ty":"sh","ix":1,"ks":{"a":0,"k":{"i":[[16.016,0],[0,0],[0,16.016],[0,0],[-16.016,0],[0,0],[0,-16.016],[0,0]],"o":[[0,0],[-16.016,0],[0,0],[0,-16.016],[0,0],[16.016,0],[0,0],[0,16.016]],"v":[[111.798,187.003],[-111.798,187.003],[-140.798,158.003],[-140.798,-158.003],[-111.798,-187.003],[111.798,-187.003],[140.798,-158.003],[140.798,158.003]],"c":true}},"nm":"Path 1","mn":"ADBE Vector Shape - Group"},{"ty":"st","c":{"a":0,"k":[0.616,0.039,0.082,1]},"o":{"a":0,"k":100},"w":{"a":0,"k":47},"lc":1,"lj":1,"ml":10,"nm":"Stroke 1","mn":"ADBE Vector Graphic - Stroke"},{"ty":"tr","p":{"a":0,"k":[258.298,304.503],"ix":2},"a":{"a":0,"k":[0,0],"ix":1},"s":{"a":0,"k":[100,100],"ix":3},"r":{"a":0,"k":0,"ix":6},"o":{"a":0,"k":100,"ix":7},"sk":{"a":0,"k":0,"ix":4},"sa":{"a":0,"k":0,"ix":5},"nm":"Transform"}],"nm":"Group 1","np":2,"cix":2,"ix":1,"mn":"ADBE Vector Group"}],"ip":-21,"op":99,"st":-21,"bm":0},{"ddd":0,"ind":15,"ty":4,"nm":"strike","parent":17,"sr":1,"ks":{"o":{"a":0,"k":100},"r":{"a":0,"k":0},"p":{"a":0,"k":[152.84,67.095,0]},"a":{"a":0,"k":[101.852,33.779,0]},"s":{"a":1,"k":[{"t":-4,"s":[100,100,100],"h":1},{"i":{"x":[0.667,0.667,0.667],"y":[1,1,1]},"o":{"x":[0.333,0.333,0.333],"y":[0,0,0]},"n":["0p667_1_0p333_0","0p667_1_0p333_0","0p667_1_0p333_0"],"t":4,"s":[100,100,100],"e":[96,96,100]},{"i":{"x":[0.667,0.667,0.667],"y":[1,1,1]},"o":{"x":[0.054,0.054,0.333],"y":[0.109,0.109,0]},"n":["0p667_1_0p054_0p109","0p667_1_0p054_0p109","0p667_1_0p333_0"],"t":6,"s":[96,96,100],"e":[94,94,100]},{"i":{"x":[0.667,0.667,0.667],"y":[1,1,1]},"o":{"x":[1,1,0.333],"y":[-0.023,-0.023,0]},"n":["0p667_1_1_-0p023","0p667_1_1_-0p023","0p667_1_0p333_0"],"t":8,"s":[94,94,100],"e":[106,106,100]},{"i":{"x":[0.667,0.667,0.667],"y":[1,1,1]},"o":{"x":[0.232,0.232,0.333],"y":[0.304,0.304,0]},"n":["0p667_1_0p232_0p304","0p667_1_0p232_0p304","0p667_1_0p333_0"],"t":10,"s":[106,106,100],"e":[108,108,100]},{"i":{"x":[0.667,0.667,0.667],"y":[1,1,1]},"o":{"x":[0.333,0.333,0.333],"y":[0,0,0]},"n":["0p667_1_0p333_0","0p667_1_0p333_0","0p667_1_0p333_0"],"t":12,"s":[108,108,100],"e":[106,106,100]},{"i":{"x":[0.667,0.667,0.667],"y":[1,1,1]},"o":{"x":[0.232,0.232,0.333],"y":[0,0,0]},"n":["0p667_1_0p232_0","0p667_1_0p232_0","0p667_1_0p333_0"],"t":14,"s":[106,106,100],"e":[97,97,100]},{"i":{"x":[0.667,0.667,0.667],"y":[1,1,1]},"o":{"x":[0.333,0.333,0.333],"y":[0,0,0]},"n":["0p667_1_0p333_0","0p667_1_0p333_0","0p667_1_0p333_0"],"t":16,"s":[97,97,100],"e":[101.5,101.5,100]},{"i":{"x":[0.833,0.833,0.833],"y":[0.833,0.833,1]},"o":{"x":[0.167,0.167,0.167],"y":[-0.002,-0.002,0]},"n":["0p833_0p833_0p167_-0p002","0p833_0p833_0p167_-0p002","0p833_1_0p167_0"],"t":20,"s":[101.5,101.5,100],"e":[100,100,100]},{"t":24}]}},"ao":0,"shapes":[{"ty":"gr","it":[{"ind":0,"ty":"sh","ix":1,"ks":{"a":0,"k":{"i":[[0,0],[0.157,-15.597],[0,0],[0.408,18.36]],"o":[[-0.44,15.976],[0,0],[-0.314,-13.369],[0,0]],"v":[[5.767,-33.143],[4.872,14.217],[-5.579,14.452],[-6.662,-33.143]],"c":true}},"nm":"Path 1","mn":"ADBE Vector Shape - Group"},{"ind":1,"ty":"sh","ix":2,"ks":{"a":0,"k":{"i":[[1.915,0],[1.349,1.349],[0,1.884],[-1.349,1.349],[-1.883,0],[-1.35,-1.35],[0,-1.914],[1.35,-1.35]],"o":[[-1.883,0],[-1.349,-1.35],[0,-1.914],[1.349,-1.35],[1.915,0],[1.35,1.349],[0,1.884],[-1.35,1.349]],"v":[[-0.024,33.143],[-4.873,31.119],[-6.897,26.269],[-4.873,21.374],[-0.024,19.349],[4.872,21.374],[6.897,26.269],[4.872,31.119]],"c":true}},"nm":"Path 2","mn":"ADBE Vector Shape - Group"},{"ty":"mm","mm":1,"nm":"Merge Paths 1","mn":"ADBE Vector Filter - Merge"},{"ty":"fl","c":{"a":0,"k":[1,1,1,1]},"o":{"a":0,"k":100},"r":1,"nm":"Fill 1","mn":"ADBE Vector Graphic - Fill"},{"ty":"tr","p":{"a":0,"k":[196.822,34.334],"ix":2},"a":{"a":0,"k":[0,0],"ix":1},"s":{"a":0,"k":[100,100],"ix":3},"r":{"a":0,"k":0,"ix":6},"o":{"a":0,"k":100,"ix":7},"sk":{"a":0,"k":0,"ix":4},"sa":{"a":0,"k":0,"ix":5},"nm":"Transform"}],"nm":"Group 1","np":4,"cix":2,"ix":1,"mn":"ADBE Vector Group"},{"ty":"gr","it":[{"ind":0,"ty":"sh","ix":1,"ks":{"a":0,"k":{"i":[[0.376,-6.465],[0,0],[0,0],[3.231,0]],"o":[[0,0],[0,0],[0,-5.712],[-3.484,0]],"v":[[-6.355,-5.485],[4.283,-5.485],[4.283,-6.615],[-0.564,-15.183]],"c":true}},"nm":"e-hole","mn":"ADBE Vector Shape - Group"},{"ty":"fl","c":{"a":0,"k":[0.7647059,0.1176471,0.1647059,1]},"o":{"a":0,"k":100},"r":1,"nm":"Fill 1","mn":"ADBE Vector Graphic - Fill"},{"ty":"tr","p":{"a":0,"k":[170.953,43.067],"ix":2},"a":{"a":0,"k":[0,0],"ix":1},"s":{"a":0,"k":[100,100],"ix":3},"r":{"a":0,"k":0,"ix":6},"o":{"a":0,"k":100,"ix":7},"sk":{"a":0,"k":0,"ix":4},"sa":{"a":0,"k":0,"ix":5},"nm":"Transform"}],"nm":"e-hole","np":2,"cix":2,"ix":2,"mn":"ADBE Vector Group"},{"ty":"gr","it":[{"ind":0,"ty":"sh","ix":1,"ks":{"a":0,"k":{"i":[[-10.2,0],[0,-14.468],[0.157,-2.008],[0,0],[-3.108,0],[0,0],[0,3.954],[0.125,1.036],[0,0],[10.451,-0.156],[0.094,0],[0,15.096],[0,0]],"o":[[10.89,0],[0,1.758],[0,0],[0,8.067],[0,0],[2.731,-0.219],[0,-0.848],[0,0],[0,11.958],[-0.126,0.033],[-9.95,0],[0,0],[0.313,-16.196]],"v":[[-0.282,-24.174],[16.054,-2.472],[15.817,3.177],[-5.226,3.177],[-0.564,15.276],[-0.235,15.276],[3.86,9.015],[3.671,6.19],[14.877,5.954],[-0.8,24.126],[-1.13,24.174],[-16.054,1.53],[-16.054,0.118]],"c":true}},"nm":"e-body","mn":"ADBE Vector Shape - Group"},{"ty":"fl","c":{"a":0,"k":[1,1,1,1]},"o":{"a":0,"k":100},"r":1,"nm":"Fill 1","mn":"ADBE Vector Graphic - Fill"},{"ty":"tr","p":{"a":0,"k":[170.953,43.067],"ix":2},"a":{"a":0,"k":[0,0],"ix":1},"s":{"a":0,"k":[100,100],"ix":3},"r":{"a":0,"k":0,"ix":6},"o":{"a":0,"k":100,"ix":7},"sk":{"a":0,"k":0,"ix":4},"sa":{"a":0,"k":0,"ix":5},"nm":"Transform"}],"nm":"e-body","np":2,"cix":2,"ix":3,"mn":"ADBE Vector Group"},{"ty":"gr","it":[{"ind":0,"ty":"sh","ix":1,"ks":{"a":0,"k":{"i":[[0,0],[0,0],[-3.83,6.183],[0,0],[4.237,-7.061],[-6.246,-10.294],[0,0],[4.393,6.685],[0,0],[0,0],[0,25.297]],"o":[[0,0],[4.299,-6.653],[0,0],[-5.681,7.909],[3.578,6.434],[0,0],[-3.515,-7.626],[0,0],[0,0],[0.219,-16.697],[0,0]],"v":[[-5.838,-33.566],[-6.026,2.918],[6.167,-16.336],[16.995,-15.112],[2.118,7.344],[16.853,32.436],[5.178,33.566],[-6.685,12.099],[-6.685,30.176],[-16.995,30.365],[-16.666,-32.625]],"c":true}},"nm":"Path 1","mn":"ADBE Vector Shape - Group"},{"ty":"fl","c":{"a":0,"k":[1,1,1,1]},"o":{"a":0,"k":100},"r":1,"nm":"Fill 1","mn":"ADBE Vector Graphic - Fill"},{"ty":"tr","p":{"a":0,"k":[134.703,33.816],"ix":2},"a":{"a":0,"k":[0,0],"ix":1},"s":{"a":0,"k":[100,100],"ix":3},"r":{"a":0,"k":0,"ix":6},"o":{"a":0,"k":100,"ix":7},"sk":{"a":0,"k":0,"ix":4},"sa":{"a":0,"k":0,"ix":5},"nm":"Transform"}],"nm":"Group 3","np":2,"cix":2,"ix":4,"mn":"ADBE Vector Group"},{"ty":"gr","it":[{"ind":0,"ty":"sh","ix":1,"ks":{"a":0,"k":{"i":[[0,0],[0,13.37],[0,0],[0,-12.648],[-0.032,-3.358]],"o":[[-0.22,-18.36],[0,0],[-0.377,12.805],[0,3.39],[0,0]],"v":[[-5.72,33.143],[-6.05,-14.453],[5.814,-15.159],[5.249,23.021],[5.296,33.143]],"c":true}},"nm":"Path 1","mn":"ADBE Vector Shape - Group"},{"ind":1,"ty":"sh","ix":2,"ks":{"a":0,"k":{"i":[[0,-1.883],[1.349,-1.349],[1.914,0],[1.349,1.35],[0,1.915],[-1.349,1.35],[-1.883,0],[-1.35,-1.349]],"o":[[0,1.915],[-1.35,1.35],[-1.883,0],[-1.349,-1.349],[0,-1.883],[1.349,-1.349],[1.914,0],[1.349,1.35]],"v":[[6.897,-26.269],[4.872,-21.373],[-0.024,-19.348],[-4.873,-21.373],[-6.897,-26.269],[-4.873,-31.118],[-0.024,-33.143],[4.872,-31.118]],"c":true}},"nm":"Path 2","mn":"ADBE Vector Shape - Group"},{"ty":"mm","mm":1,"nm":"Merge Paths 1","mn":"ADBE Vector Filter - Merge"},{"ty":"fl","c":{"a":0,"k":[1,1,1,1]},"o":{"a":0,"k":100},"r":1,"nm":"Fill 1","mn":"ADBE Vector Graphic - Fill"},{"ty":"tr","p":{"a":0,"k":[107.845,34.334],"ix":2},"a":{"a":0,"k":[0,0],"ix":1},"s":{"a":0,"k":[100,100],"ix":3},"r":{"a":0,"k":0,"ix":6},"o":{"a":0,"k":100,"ix":7},"sk":{"a":0,"k":0,"ix":4},"sa":{"a":0,"k":0,"ix":5},"nm":"Transform"}],"nm":"Group 4","np":4,"cix":2,"ix":5,"mn":"ADBE Vector Group"},{"ty":"gr","it":[{"ind":0,"ty":"sh","ix":1,"ks":{"a":0,"k":{"i":[[0.69,-2.824],[0,0],[0,0],[0.972,17.983],[0,0],[0,0],[-4.833,0.534],[-0.659,0],[-1.977,-2.48],[-0.032,-6.433],[0,0],[0,0.502],[2.605,0],[0,0]],"o":[[0,0],[0,0],[0,-14.437],[0,0],[0,0],[1.319,-3.765],[0.722,-0.063],[3.797,0],[2.291,2.95],[0,0],[0.031,-0.533],[0,-5.022],[0,0],[-3.013,0.159]],"v":[[-3.766,-9.439],[-3.296,24.692],[-14.83,24.787],[-16.288,-23.844],[-7.627,-24.787],[-7.157,-17.113],[2.07,-23.562],[4.143,-23.657],[12.804,-19.937],[16.288,-5.861],[5.837,-4.826],[5.884,-6.378],[1.976,-13.912],[1.788,-13.912]],"c":true}},"nm":"Path 1","mn":"ADBE Vector Shape - Group"},{"ty":"fl","c":{"a":0,"k":[1,1,1,1]},"o":{"a":0,"k":100},"r":1,"nm":"Fill 1","mn":"ADBE Vector Graphic - Fill"},{"ty":"tr","p":{"a":0,"k":[82.117,42.925],"ix":2},"a":{"a":0,"k":[0,0],"ix":1},"s":{"a":0,"k":[100,100],"ix":3},"r":{"a":0,"k":0,"ix":6},"o":{"a":0,"k":100,"ix":7},"sk":{"a":0,"k":0,"ix":4},"sa":{"a":0,"k":0,"ix":5},"nm":"Transform"}],"nm":"Group 5","np":2,"cix":2,"ix":6,"mn":"ADBE Vector Group"},{"ty":"gr","it":[{"ind":0,"ty":"sh","ix":1,"ks":{"a":0,"k":{"i":[[0,0],[0,0],[0,0],[0,0],[0,0],[0,0],[0,0],[-4.237,0],[-1.036,0.22],[0,0],[1.349,0],[0.188,10.233],[0,0],[0,0],[0,0],[0,0]],"o":[[0,0],[0,0],[0,0],[0,0],[0,0],[0,0],[0,4.99],[0.878,0],[0,0],[-1.507,0.187],[-9.918,0],[0,0],[0,0],[0,0],[0,0],[0,0]],"v":[[-6.026,-31.236],[4.661,-31.942],[4.661,-16.36],[13.652,-16.595],[13.793,-7.698],[4.661,-7.274],[4.661,14.146],[11.016,21.631],[13.888,21.302],[13.464,31.66],[9.18,31.942],[-5.979,16.594],[-5.979,-6.426],[-13.7,-5.956],[-13.888,-16.454],[-5.979,-16.36]],"c":true}},"nm":"Path 1","mn":"ADBE Vector Shape - Group"},{"ty":"fl","c":{"a":0,"k":[1,1,1,1]},"o":{"a":0,"k":100},"r":1,"nm":"Fill 1","mn":"ADBE Vector Graphic - Fill"},{"ty":"tr","p":{"a":0,"k":[48.127,35.111],"ix":2},"a":{"a":0,"k":[0,0],"ix":1},"s":{"a":0,"k":[100,100],"ix":3},"r":{"a":0,"k":0,"ix":6},"o":{"a":0,"k":100,"ix":7},"sk":{"a":0,"k":0,"ix":4},"sa":{"a":0,"k":0,"ix":5},"nm":"Transform"}],"nm":"Group 6","np":2,"cix":2,"ix":7,"mn":"ADBE Vector Group"},{"ty":"gr","it":[{"ind":0,"ty":"sh","ix":1,"ks":{"a":0,"k":{"i":[[0.062,7.219],[0,0],[0,0],[-2.982,-0.062],[0,0],[0,2.794],[0,0],[5.57,1.883],[1.13,4.457],[0,1.445],[-1.35,2.26],[-4.206,0.502],[-1.068,0],[-2.134,-0.972],[-1.13,-2.51],[0,-2.101],[0.156,-1.067],[0,0],[0,0.658],[2.008,0.221],[0.219,0],[0.722,-2.103],[0,-0.596],[-1.381,-1.068],[-3.814,-1.553],[-1.318,-3.735],[0,-1.412],[1.38,-2.416],[4.613,-0.628],[0.972,0],[2.95,1.789]],"o":[[0,0],[0,0],[0,4.834],[0,0],[2.887,0],[0,0],[-0.126,-3.075],[-5.572,-1.882],[-0.408,-1.569],[0,-2.636],[2.072,-3.452],[1.13,-0.125],[2.793,0],[2.919,1.35],[0.753,1.727],[0,1.005],[0,0],[0.094,-0.784],[0,-3.138],[-0.22,-0.03],[-2.071,0],[-0.251,0.722],[0,1.476],[1.946,1.505],[3.813,1.554],[0.471,1.412],[0,2.386],[-2.197,3.861],[-1.005,0.157],[-3.453,0],[-3.766,-2.291]],"v":[[-15.3,7.532],[-4.519,7.015],[-4.519,7.627],[-0.047,14.971],[0.141,14.971],[4.472,10.781],[4.472,10.451],[-4.072,3.012],[-14.123,-6.497],[-14.735,-11.016],[-12.711,-18.36],[-3.296,-24.291],[0,-24.481],[7.391,-23.02],[13.464,-17.231],[14.594,-11.488],[14.359,-8.38],[4.284,-8.144],[4.425,-10.309],[1.412,-15.347],[0.753,-15.394],[-3.437,-12.239],[-3.813,-10.262],[-1.742,-6.449],[6.897,-1.86],[14.594,6.074],[15.3,10.309],[13.229,17.512],[3.013,24.245],[0.047,24.481],[-9.557,21.798]],"c":true}},"nm":"Path 1","mn":"ADBE Vector Shape - Group"},{"ty":"fl","c":{"a":0,"k":[1,1,1,1]},"o":{"a":0,"k":100},"r":1,"nm":"Fill 1","mn":"ADBE Vector Graphic - Fill"},{"ty":"tr","p":{"a":0,"k":[15.55,42.996],"ix":2},"a":{"a":0,"k":[0,0],"ix":1},"s":{"a":0,"k":[100,100],"ix":3},"r":{"a":0,"k":0,"ix":6},"o":{"a":0,"k":100,"ix":7},"sk":{"a":0,"k":0,"ix":4},"sa":{"a":0,"k":0,"ix":5},"nm":"Transform"}],"nm":"Group 7","np":2,"cix":2,"ix":8,"mn":"ADBE Vector Group"}],"ip":-21,"op":99,"st":-21,"bm":0},{"ddd":0,"ind":17,"ty":4,"nm":"bubble","parent":5,"sr":1,"ks":{"o":{"a":0,"k":100},"r":{"a":0,"k":0},"p":{"a":0,"k":[258.298,304.503,0]},"a":{"a":0,"k":[153.757,-230.738,0]},"s":{"a":1,"k":[{"t":-4,"s":[100,100,100],"h":1},{"i":{"x":[0.667,0.667,0.667],"y":[1,1,1]},"o":{"x":[0.333,0.333,0.333],"y":[0,0,0]},"n":["0p667_1_0p333_0","0p667_1_0p333_0","0p667_1_0p333_0"],"t":4,"s":[100,100,100],"e":[99,99,100]},{"i":{"x":[0.667,0.667,0.667],"y":[1,1,1]},"o":{"x":[0.054,0.054,0.333],"y":[0.218,0.218,0]},"n":["0p667_1_0p054_0p218","0p667_1_0p054_0p218","0p667_1_0p333_0"],"t":6,"s":[99,99,100],"e":[98,98,100]},{"i":{"x":[0.667,0.667,0.667],"y":[1,1,1]},"o":{"x":[1,1,0.333],"y":[-0.091,-0.091,0]},"n":["0p667_1_1_-0p091","0p667_1_1_-0p091","0p667_1_0p333_0"],"t":8,"s":[98,98,100],"e":[101,101,100]},{"i":{"x":[0.667,0.667,0.667],"y":[1,1,1]},"o":{"x":[0.232,0.232,0.333],"y":[0.608,0.608,0]},"n":["0p667_1_0p232_0p608","0p667_1_0p232_0p608","0p667_1_0p333_0"],"t":10,"s":[101,101,100],"e":[102,102,100]},{"i":{"x":[0.667,0.667,0.667],"y":[1,1,1]},"o":{"x":[0.333,0.333,0.333],"y":[0,0,0]},"n":["0p667_1_0p333_0","0p667_1_0p333_0","0p667_1_0p333_0"],"t":12,"s":[102,102,100],"e":[101,101,100]},{"i":{"x":[0.667,0.667,0.667],"y":[1,1,1]},"o":{"x":[0.232,0.232,0.333],"y":[0,0,0]},"n":["0p667_1_0p232_0","0p667_1_0p232_0","0p667_1_0p333_0"],"t":14,"s":[101,101,100],"e":[99.5,99.5,100]},{"i":{"x":[0.667,0.667,0.667],"y":[1,1,1]},"o":{"x":[0.333,0.333,0.333],"y":[0,0,0]},"n":["0p667_1_0p333_0","0p667_1_0p333_0","0p667_1_0p333_0"],"t":16,"s":[99.5,99.5,100],"e":[100.5,100.5,100]},{"i":{"x":[0.833,0.833,0.833],"y":[0.833,0.833,0.836]},"o":{"x":[0.167,0.167,0.167],"y":[-0.007,-0.007,0]},"n":["0p833_0p833_0p167_-0p007","0p833_0p833_0p167_-0p007","0p833_0p836_0p167_0"],"t":20,"s":[100.5,100.5,100],"e":[100,100,100]},{"t":24}]}},"ao":0,"shapes":[{"ty":"gr","it":[{"ind":0,"ty":"sh","ix":1,"ks":{"a":0,"k":{"i":[[16.016,0],[0,0],[0,16.016],[0,0],[-16.017,0],[0,0],[0,-16.016],[0,0]],"o":[[0,0],[-16.017,0],[0,0],[0,-16.016],[0,0],[16.016,0],[0,0],[0,16.016]],"v":[[123.5,67.941],[-123.5,67.941],[-152.5,38.941],[-152.5,-38.941],[-123.5,-67.941],[123.5,-67.941],[152.5,-38.941],[152.5,38.941]],"c":true}},"nm":"Path 1","mn":"ADBE Vector Shape - Group"},{"ty":"fl","c":{"a":0,"k":[0.765,0.118,0.165,1]},"o":{"a":0,"k":100},"r":1,"nm":"Fill 1","mn":"ADBE Vector Graphic - Fill"},{"ty":"tr","p":{"a":0,"k":[152.75,68.19],"ix":2},"a":{"a":0,"k":[0,0],"ix":1},"s":{"a":0,"k":[100,100],"ix":3},"r":{"a":0,"k":0,"ix":6},"o":{"a":0,"k":100,"ix":7},"sk":{"a":0,"k":0,"ix":4},"sa":{"a":0,"k":0,"ix":5},"nm":"Transform"}],"nm":"Group 1","np":2,"cix":2,"ix":1,"mn":"ADBE Vector Group"}],"ip":-21,"op":99,"st":-21,"bm":0},{"ddd":0,"ind":18,"ty":4,"nm":"bubble_shadow","parent":17,"sr":1,"ks":{"o":{"a":0,"k":100},"r":{"a":0,"k":0},"p":{"a":0,"k":[152.75,75.19,0]},"a":{"a":0,"k":[152.75,68.19,0]},"s":{"a":0,"k":[100,100,100]}},"ao":0,"shapes":[{"ty":"gr","it":[{"ind":0,"ty":"sh","ix":1,"ks":{"a":0,"k":{"i":[[16.016,0],[0,0],[0,16.016],[0,0],[-16.017,0],[0,0],[0,-16.016],[0,0]],"o":[[0,0],[-16.017,0],[0,0],[0,-16.016],[0,0],[16.016,0],[0,0],[0,16.016]],"v":[[123.5,67.941],[-123.5,67.941],[-152.5,38.941],[-152.5,-38.941],[-123.5,-67.941],[123.5,-67.941],[152.5,-38.941],[152.5,38.941]],"c":true}},"nm":"Path 1","mn":"ADBE Vector Shape - Group"},{"ty":"fl","c":{"a":0,"k":[0.616,0.039,0.082,1]},"o":{"a":0,"k":100},"r":1,"nm":"Fill 1","mn":"ADBE Vector Graphic - Fill"},{"ty":"tr","p":{"a":0,"k":[152.75,68.19],"ix":2},"a":{"a":0,"k":[0,0],"ix":1},"s":{"a":0,"k":[100,100],"ix":3},"r":{"a":0,"k":0,"ix":6},"o":{"a":0,"k":100,"ix":7},"sk":{"a":0,"k":0,"ix":4},"sa":{"a":0,"k":0,"ix":5},"nm":"Transform"}],"nm":"Group 1","np":2,"cix":2,"ix":1,"mn":"ADBE Vector Group"}],"ip":-21,"op":99,"st":-21,"bm":0}]}